<?xml version="1.0" ?><timetable station="Erfurt Hbf" eva="8010101">

<s id="6289498206777184904-2505041226-20" eva="8010101">
    <ar ct="2505041508" l="RE10"/>
</s>


<s id="4070823581815571945-2505041426-19" eva="8010101">
    <ar ct="2505041651" l="RE10"/>
</s>


<s id="3687002688544572631-2505041409-23" eva="8010101">
    <ar cpth="Leipzig-Leutzsch|Leipzig-Rückmarsdorf|Leipzig-Miltitz|Markranstädt|Großlehna|Kötzschau|Bad Dürrenberg|Großkorbetha|Weißenfels|Leißling|Naumburg(Saale)Hbf|Bad Kösen|Großheringen|Bad Sulza|Niedertrebra|Apolda|Oßmannstedt|Weimar|Hopfgarten(Weimar)|Vieselbach" ct="2505041602" l="20">
        <m id="r17209746" t="d" c="38" ts="2505041349" ts-tts="25-05-04 13:49:16.349"/>
        <m id="r17211239" t="d" c="48" ts="2505041430" ts-tts="25-05-04 14:30:45.109"/>
    </ar>
    <dp cpth="Erfurt-Bischleben|Neudietendorf|Wandersleben|Seebergen|Gotha|Fröttstädt|Mechterstädt|Sättelstädt|Schönau(Hörsel)|Wutha|Eisenach Hbf" ct="2505041604" l="20">
        <m id="r17209746" t="d" c="38" ts="2505041349" ts-tts="25-05-04 13:49:16.349"/>
        <m id="r17211239" t="d" c="48" ts="2505041430" ts-tts="25-05-04 14:30:45.109"/>
    </dp>
</s>


<s id="-4803413020616385260-2505041118-9" eva="8010101">
    <m id="r2413050" t="h" from="2505011915" to="2505052359" cat="Information" ts="2505011920" ts-tts="25-05-03 23:16:03.739" pr="2"/>
    <ar ct="2505041555">
        <m id="r17205038" t="d" c="47" ts="2505041108" ts-tts="25-05-04 11:08:24.909"/>
        <m id="r17205582" t="f" c="0" ts="2505041127" ts-tts="25-05-04 11:27:42.552"/>
        <m id="r17206224" t="f" c="0" ts="2505041148" ts-tts="25-05-04 11:48:18.271"/>
        <m id="r17206900" t="f" c="0" ts="2505041214" ts-tts="25-05-04 12:14:17.355"/>
    </ar>
    <dp ct="2505041557">
        <m id="r17205038" t="d" c="47" ts="2505041108" ts-tts="25-05-04 11:08:24.909"/>
        <m id="r17205582" t="f" c="0" ts="2505041127" ts-tts="25-05-04 11:27:42.552"/>
        <m id="r17206224" t="f" c="0" ts="2505041148" ts-tts="25-05-04 11:48:18.271"/>
        <m id="r17206900" t="f" c="0" ts="2505041214" ts-tts="25-05-04 12:14:17.355"/>
    </dp>
</s>


<s id="-8657781205239698076-2505041406-12" eva="8010101">
    <ar ct="2505041456" l="20">
        <m id="r17209184" t="d" c="48" ts="2505041334" ts-tts="25-05-04 13:34:19.886"/>
    </ar>
    <dp ct="2505041504" l="20">
        <m id="r17209184" t="d" c="48" ts="2505041334" ts-tts="25-05-04 13:34:19.886"/>
    </dp>
</s>


<s id="-8385239583586491560-2505041511-1" eva="8010101">
    <dp ct="2505041539" l="51">
        <m id="r17125141" t="f" c="0" ts="2505021200" ts-tts="25-05-02 12:00:33.305"/>
        <m id="r17125286" t="d" c="31" ts="2505021201" ts-tts="25-05-02 12:01:35.778"/>
        <m id="r17159353" t="f" c="0" ts="2505030151" ts-tts="25-05-03 01:51:30.381"/>
        <m id="r17159364" t="d" c="31" ts="2505030151" ts-tts="25-05-03 01:51:30.381"/>
    </dp>
</s>


<s id="-3331034907260447336-2505040919-13" eva="8010101">
    <m id="r2414360" t="h" from="2505040915" to="2505041000" cat="Störung" ts="2505040943" ts-tts="25-05-04 09:43:20.576" pr="2"/>
    <m id="r2414385" t="h" from="2505041030" to="2505041130" cat="Störung" ts="2505041054" ts-tts="25-05-04 10:54:31.769" pr="2"/>
    <ar ppth="Köln Hbf|Düsseldorf Hbf|Düsseldorf Flughafen|Duisburg Hbf|Essen Hbf|Bochum Hbf|Dortmund Hbf|Hamm(Westf)Hbf|Hannover Hbf|Göttingen|Eisenach Hbf|Gotha" cp="10" ct="2505041536" pt="2505041509">
        <m id="r17125248" t="d" c="31" ts="2505021201" ts-tts="25-05-02 12:01:04.512"/>
        <m id="r17125287" t="d" c="31" ts="2505021201" ts-tts="25-05-02 12:01:35.778"/>
        <m id="r17155109" t="d" c="31" ts="2505022252" ts-tts="25-05-02 22:53:00.958"/>
        <m id="r17159362" t="d" c="31" ts="2505030151" ts-tts="25-05-03 01:51:30.380"/>
        <m id="r17159366" t="d" c="31" ts="2505030151" ts-tts="25-05-03 01:51:30.380"/>
        <m id="r17159856" t="d" c="31" ts="2505030152" ts-tts="25-05-03 01:52:47.257"/>
        <m id="r17203702" t="d" c="7" ts="2505041011" ts-tts="25-05-04 10:11:22.041"/>
        <m id="r17207782" t="f" c="0" ts="2505041243" ts-tts="25-05-04 12:43:38.802"/>
        <m id="r17209481" t="d" c="38" ts="2505041342" ts-tts="25-05-04 13:42:18.872"/>
        <m id="r17209745" t="f" c="0" ts="2505041349" ts-tts="25-05-04 13:49:16.349"/>
    </ar>
    <dp ppth="Weimar|Jena West|Jena-Göschwitz|Stadtroda|Hermsdorf-Klosterlausnitz|Gera Hbf" cp="10" ct="2505041539" pt="2505041511">
        <m id="r17125248" t="d" c="31" ts="2505021201" ts-tts="25-05-02 12:01:04.513"/>
        <m id="r17125287" t="d" c="31" ts="2505021201" ts-tts="25-05-02 12:01:35.778"/>
        <m id="r17155109" t="d" c="31" ts="2505022252" ts-tts="25-05-02 22:53:00.958"/>
        <m id="r17159362" t="d" c="31" ts="2505030151" ts-tts="25-05-03 01:51:30.380"/>
        <m id="r17159366" t="d" c="31" ts="2505030151" ts-tts="25-05-03 01:51:30.380"/>
        <m id="r17159856" t="d" c="31" ts="2505030152" ts-tts="25-05-03 01:52:47.257"/>
        <m id="r17203702" t="d" c="7" ts="2505041011" ts-tts="25-05-04 10:11:22.042"/>
        <m id="r17207782" t="f" c="0" ts="2505041243" ts-tts="25-05-04 12:43:38.802"/>
        <m id="r17209481" t="d" c="38" ts="2505041342" ts-tts="25-05-04 13:42:18.872"/>
        <m id="r17209745" t="f" c="0" ts="2505041349" ts-tts="25-05-04 13:49:16.349"/>
    </dp>
    <tl f="F" t="e" o="80" c="IC" n="2575"/>
</s>


<s id="-2938250141698044711-2505041309-23" eva="8010101">
    <ar ct="2505041512" l="20">
        <m id="r17208725" t="d" c="48" ts="2505041317" ts-tts="25-05-04 13:17:36.767"/>
        <m id="r17210702" t="d" c="38" ts="2505041417" ts-tts="25-05-04 14:17:36.181"/>
    </ar>
    <dp ct="2505041514" l="20">
        <m id="r17208725" t="d" c="48" ts="2505041317" ts-tts="25-05-04 13:17:36.767"/>
        <m id="r17210702" t="d" c="38" ts="2505041417" ts-tts="25-05-04 14:17:36.181"/>
    </dp>
</s>


<s id="7972492914704714215-2505041121-7" eva="8010101">
    <ar ct="2505041532">
        <m id="r17205906" t="d" c="34" ts="2505041138" ts-tts="25-05-04 11:38:16.228"/>
        <m id="r17206285" t="f" c="0" ts="2505041150" ts-tts="25-05-04 11:50:21.602"/>
    </ar>
    <dp ct="2505041534">
        <m id="r17205906" t="d" c="34" ts="2505041138" ts-tts="25-05-04 11:38:16.228"/>
        <m id="r17206285" t="f" c="0" ts="2505041150" ts-tts="25-05-04 11:50:21.602"/>
    </dp>
</s>


<s id="5388399388935565669-2505041502-2" eva="8010101">
    <ar ct="2505041709"/>
    <dp ct="2505041714"/>
</s>


<s id="6316301349186864660-2505041502-4" eva="8010101">
    <ar ct="2505041538" l="3"/>
</s>


<s id="-2543008509222161707-2505040630-9" eva="8010101">
    <m id="r2414101" t="h" from="2505040630" to="2505041836" cat="Information" ts="2505040021" ts-tts="25-05-04 00:21:55.122" pr="2"/>
    <ar ct="2505041429">
        <m id="r17207466" t="d" c="43" ts="2505041232" ts-tts="25-05-04 12:32:50.348"/>
    </ar>
    <dp ct="2505041432">
        <m id="r17207466" t="d" c="43" ts="2505041232" ts-tts="25-05-04 12:32:50.348"/>
    </dp>
</s>


<s id="-1080248324669897140-2505041502-1" eva="8010101">
    <dp ct="2505041502" l="56">
        <m id="r17190538" t="f" c="0" ts="2505032045" ts-tts="25-05-03 20:45:10.148"/>
        <m id="r17198882" t="q" c="93" ts="2505040340" ts-tts="25-05-04 03:40:48.966"/>
    </dp>
</s>


<s id="7466374885851559178-2505041306-14" eva="8010101">
    <ar ct="2505041523" l="2">
        <m id="r17191581" t="f" c="0" ts="2505032118" ts-tts="25-05-03 21:18:14.113"/>
    </ar>
</s>


<s id="3347962458976406336-2505041252-5" eva="8010101">
    <m id="r2414263" t="h" from="2505041252" to="2505041710" cat="Information" ts="2505040732" ts-tts="25-05-04 07:32:53.880" pr="3"/>
    <ar ppth="Berlin Gesundbrunnen|Berlin Hbf|Berlin Südkreuz|Halle(Saale)Hbf" pp="1" ct="2505041502" pt="2505041448">
        <m id="r17200364" t="f" c="0" ts="2505040710" ts-tts="25-05-04 07:11:06.675"/>
    </ar>
    <dp ppth="Nürnberg Hbf|München Hbf" pp="1" ct="2505041504" pt="2505041450">
        <m id="r17200364" t="f" c="0" ts="2505040710" ts-tts="25-05-04 07:11:06.675"/>
    </dp>
    <tl f="F" t="e" o="80" c="ICE" n="2919"/>
    <ref>
        <tl f="F" t="p" o="80" c="ICE" n="1109"/>
    </ref>
</s>


<s id="-1099707498340369858-2505040901-8" eva="8010101">
    <ar ct="2505041626">
        <m id="r17199242" t="f" c="0" ts="2505040508" ts-tts="25-05-04 05:08:48.419"/>
        <m id="r17200668" t="f" c="0" ts="2505040723" ts-tts="25-05-04 07:23:24.771"/>
        <m id="r17207925" t="d" c="43" ts="2505041249" ts-tts="25-05-04 12:49:18.687"/>
        <m id="r17211209" t="q" c="97" ts="2505041429" ts-tts="25-05-04 14:29:43.310"/>
    </ar>
    <dp ct="2505041628">
        <m id="r17199242" t="f" c="0" ts="2505040508" ts-tts="25-05-04 05:08:48.419"/>
        <m id="r17200668" t="f" c="0" ts="2505040723" ts-tts="25-05-04 07:23:24.771"/>
        <m id="r17207925" t="d" c="43" ts="2505041249" ts-tts="25-05-04 12:49:18.687"/>
        <m id="r17211209" t="q" c="97" ts="2505041429" ts-tts="25-05-04 14:29:43.310"/>
    </dp>
</s>


<s id="-7242833275344733401-2505041302-2" eva="8010101">
    <ar ct="2505041507"/>
    <dp ct="2505041512"/>
</s>


<s id="5897211217521878733-2505041150-7" eva="8010101">
    <m id="r2413950" t="h" from="2505031530" to="2505050000" cat="Störung" ts="2505031622" ts-tts="25-05-04 10:16:00.962" pr="1"/>
    <ar ct="2505041551">
        <m id="r17208757" t="f" c="0" ts="2505041318" ts-tts="25-05-04 13:18:53.856"/>
        <m id="r17211163" t="f" c="0" ts="2505041428" ts-tts="25-05-04 14:28:26.093"/>
    </ar>
    <dp ct="2505041554">
        <m id="r17208757" t="f" c="0" ts="2505041318" ts-tts="25-05-04 13:18:53.856"/>
        <m id="r17211163" t="f" c="0" ts="2505041428" ts-tts="25-05-04 14:28:26.093"/>
    </dp>
</s>


<s id="3385058391639482402-2505040922-10" eva="8010101">
    <ar ct="2505041637">
        <m id="r17203912" t="d" c="43" ts="2505041020" ts-tts="25-05-04 10:20:52.748"/>
    </ar>
    <dp ct="2505041639">
        <m id="r17203912" t="d" c="43" ts="2505041020" ts-tts="25-05-04 10:20:52.748"/>
    </dp>
</s>


<s id="235347214713352060-2505041215-9" eva="8010101">
    <m id="r2413050" t="h" from="2505011915" to="2505052359" cat="Information" ts="2505011920" ts-tts="25-05-03 23:16:03.739" pr="2"/>
    <ar cpth="Hamburg-Altona|Hamburg Dammtor|Hamburg Hbf|Büchen|Berlin-Spandau|Berlin Hbf|Berlin Südkreuz|Lutherstadt Wittenberg Hbf|Leipzig Hbf" ct="2505041637">
        <m id="r17207830" t="f" c="0" ts="2505041245" ts-tts="25-05-04 12:45:57.936"/>
        <m id="r17208127" t="d" c="43" ts="2505041256" ts-tts="25-05-04 12:56:30.657"/>
    </ar>
    <dp cpth="Erlangen|Nürnberg Hbf|München Hbf" ct="2505041639">
        <m id="r17207830" t="f" c="0" ts="2505041245" ts-tts="25-05-04 12:45:57.936"/>
        <m id="r17208127" t="d" c="43" ts="2505041256" ts-tts="25-05-04 12:56:30.657"/>
    </dp>
</s>


<s id="416160715671297393-2505041402-3" eva="8010101">
    <ar ct="2505041428" l="16"/>
</s>


<s id="7263013751365542337-2505041013-11" eva="8010101">
    <m id="r2414092" t="h" from="2505041013" to="2505042013" cat="Information" ts="2505040015" ts-tts="25-05-04 00:15:39.596" pr="2"/>
    <m id="r2394668" t="h" from="2505010000" to="2506302359" cat="Information" ts="2504302303" ts-tts="25-05-03 23:16:03.453" pr="1"/>
    <ar ct="2505041619">
        <m id="r17208004" t="d" c="54" ts="2505041252" ts-tts="25-05-04 12:52:23.827"/>
    </ar>
    <dp ct="2505041621">
        <m id="r17208004" t="d" c="54" ts="2505041252" ts-tts="25-05-04 12:52:23.827"/>
    </dp>
</s>


<s id="-1588936129122896413-2505041456-5" eva="8010101">
    <m id="r2413050" t="h" from="2505011915" to="2505052359" cat="Information" ts="2505011920" ts-tts="25-05-03 23:16:03.739" pr="2"/>
    <ar ct="2505041725"/>
    <dp ct="2505041728"/>
</s>


<s id="-5731373183415360246-2505041412-14" eva="8010101">
    <ar ct="2505041517" l="23">
        <m id="r17211077" t="d" c="21" ts="2505041426" ts-tts="25-05-04 14:26:22.395"/>
    </ar>
</s>


<s id="-8006524328198881016-2505041455-8" eva="8010101">
    <ar ct="2505041923" l="10">
        <m id="r17190548" t="f" c="0" ts="2505032045" ts-tts="25-05-03 20:45:25.639"/>
        <m id="r17190549" t="f" c="1000" ts="2505032045" ts-tts="25-05-03 20:45:25.639"/>
    </ar>
    <dp ct="2505041925" l="10">
        <m id="r17190548" t="f" c="0" ts="2505032045" ts-tts="25-05-03 20:45:25.639"/>
        <m id="r17190549" t="f" c="1000" ts="2505032045" ts-tts="25-05-03 20:45:25.639"/>
    </dp>
</s>


<s id="5186490163197231839-2505041017-9" eva="8010101">
    <m id="r2413050" t="h" from="2505011915" to="2505052359" cat="Information" ts="2505011920" ts-tts="25-05-03 23:16:03.739" pr="2"/>
    <ar ct="2505041425"/>
    <dp ct="2505041431"/>
</s>


<s id="682718266047226442-2505041245-5" eva="8010101">
    <ar ct="2505041447"/>
    <dp ct="2505041449"/>
</s>


<s id="1980910822671238492-2505041113-7" eva="8010101">
    <m id="r2413050" t="h" from="2505011915" to="2505052359" cat="Information" ts="2505011920" ts-tts="25-05-03 23:16:03.739" pr="2"/>
    <ar ct="2505041425">
        <m id="r17204017" t="f" c="0" ts="2505041024" ts-tts="25-05-04 10:24:59.157"/>
        <m id="r17204026" t="d" c="48" ts="2505041025" ts-tts="25-05-04 10:25:45.411"/>
    </ar>
    <dp ct="2505041432">
        <m id="r17204017" t="f" c="0" ts="2505041024" ts-tts="25-05-04 10:24:59.157"/>
        <m id="r17204026" t="d" c="48" ts="2505041025" ts-tts="25-05-04 10:25:45.411"/>
    </dp>
</s>


<s id="5089820149948252230-2505041453-8" eva="8010101">
    <ar ct="2505042226"/>
    <dp ct="2505042228"/>
</s>


<s id="2356657928216771432-2505041323-13" eva="8010101">
    <ar ct="2505041512" l="3"/>
</s>


<s id="-1524771013898888298-2505041317-13" eva="8010101">
    <ar ct="2505041512" l="3"/>
</s>


<s id="-323524537261309369-2505041452-5" eva="8010101">
    <ar ct="2505041647"/>
    <dp ct="2505041650"/>
</s>


<s id="-5187474858684168105-2505041451-3" eva="8010101">
    <m id="r2414086" t="h" from="2505041451" to="2505050001" cat="Information" ts="2505040015" ts-tts="25-05-04 00:15:24.133" pr="2"/>
    <ar ct="2505041709"/>
    <dp ct="2505041711"/>
</s>


<s id="-2271803111890997286-2505041201-13" eva="8010101">
    <ar ct="2505041422" l="7"/>
</s>


<s id="-4237431069235454222-2505041420-1" eva="8010101">
    <dp ct="2505041421" l="3"/>
</s>


<s id="-1010657799997969211-2505041819-16" eva="8010101">
    <ar ct="2505041951" l="44"/>
</s>


<s id="3422823246203542050-2505041404-4" eva="8010101">
    <ar ct="2505041551">
        <m id="r17208758" t="f" c="0" ts="2505041318" ts-tts="25-05-04 13:18:53.856"/>
    </ar>
    <dp ct="2505041554">
        <m id="r17208758" t="f" c="0" ts="2505041318" ts-tts="25-05-04 13:18:53.856"/>
    </dp>
</s>


<s id="-3580917122362304390-2505041209-23" eva="8010101">
    <ar ct="2505041415" l="20">
        <m id="r17207834" t="d" c="48" ts="2505041245" ts-tts="25-05-04 12:45:57.936"/>
    </ar>
    <dp ct="2505041418" l="20">
        <m id="r17207834" t="d" c="48" ts="2505041245" ts-tts="25-05-04 12:45:57.936"/>
    </dp>
</s>


<s id="2256650773487823211-2505041818-14" eva="8010101">
    <ar ct="2505041917" l="46"/>
</s>


<s id="4851193275654738180-2505041652-3" eva="8010101">
    <ar>
        <m id="r17210692" t="q" c="98" ts="2505041416" ts-tts="25-05-04 14:17:05.235"/>
    </ar>
    <dp>
        <m id="r17210692" t="q" c="98" ts="2505041416" ts-tts="25-05-04 14:17:05.235"/>
    </dp>
</s>


<s id="364356506026184607-2505041312-13" eva="8010101">
    <ar ct="2505041417" l="23"/>
</s>


<s id="-4917702376265965252-2505041243-18" eva="8010101">
    <ar ct="2505041417" l="46"/>
</s>


<s id="-9139934634477843072-2505041513-12" eva="8010101">
    <ar ct="2505041558" l="20"/>
    <dp ct="2505041604" l="20"/>
</s>


<s id="2193672917151955345-2505041812-14" eva="8010101">
    <ar ct="2505041917" l="23"/>
</s>


<s id="-667854438862135023-2505041254-5" eva="8010101">
    <m id="r2413050" t="h" from="2505011915" to="2505052359" cat="Information" ts="2505011920" ts-tts="25-05-03 23:16:03.739" pr="2"/>
    <ar ct="2505041526">
        <m id="r17210516" t="d" c="43" ts="2505041411" ts-tts="25-05-04 14:11:09.660"/>
    </ar>
    <dp ct="2505041528">
        <m id="r17210516" t="d" c="43" ts="2505041411" ts-tts="25-05-04 14:11:09.660"/>
    </dp>
</s>


<s id="-8313378675731044505-2505041409-1" eva="8010101">
    <dp ct="2505041410" l="59"/>
</s>


<s id="7406533111035899891-2505041509-23" eva="8010101">
    <ar ct="2505041655" l="20"/>
    <dp ct="2505041705" l="20"/>
</s>


<s id="-442009752924376298-2505041210-5" eva="8010101">
    <ar ct="2505041411"/>
    <dp ct="2505041418"/>
</s>


<s id="4011391143588531096-2505041438-10" eva="8010101">
    <ar ct="2505041844"/>
    <dp ct="2505041847"/>
</s>


<s id="1093345759342696716-2505041251-3" eva="8010101">
    <ar ct="2505041509"/>
    <dp ct="2505041511"/>
</s>


<s id="-7601771751641911969-2505041401-13" eva="8010101">
    <ar ct="2505041620" l="7">
        <m id="r17210300" t="d" c="47" ts="2505041402" ts-tts="25-05-04 14:02:54.882"/>
    </ar>
</s>


<s id="-7211139863672830743-2505041231-11" eva="8010101">
    <ar ct="2505041408" l="1"/>
    <dp ct="2505041411" l="1"/>
</s>


<s id="789335602764010828-2505041405-1" eva="8010101">
    <dp ct="2505041405" l="44"/>
</s>


<s id="-7810134847354827599-2505041435-1" eva="8010101">
    <dp ct="2505041435" l="16"/>
</s>


<s id="-7308819124573098809-2505041805-1" eva="8010101">
    <dp ct="2505041805" l="44"/>
</s>


<s id="8807566326536598436-2505041310-1" eva="8010101">
    <dp ppth="Stotternheim|Großrudestedt|Sömmerda|Leubingen|Griefstedt|Heldrungen|Artern|Voigtstedt|Oberröblingen|Sangerhausen|Klostermansfeld|Hettstedt|Sandersleben(Anh)|Güsten|Staßfurt|Schönebeck(Elbe)|Magdeburg-Buckau|Magdeburg Hbf" cp="8" pp="5" ct="2505041405" pt="2505041310" l="RE10"/>
    <tl t="p" o="RSMD" c="SMD" n="74848"/>
</s>


<s id="8782503106492390781-2505041434-11" eva="8010101">
    <ar ct="2505041550" l="55"/>
</s>


<s id="859816784605384407-2505041313-12" eva="8010101">
    <ar ct="2505041402" l="20"/>
    <dp ct="2505041404" l="20"/>
</s>


<s id="-7334830811489709769-2505041210-9" eva="8010101">
    <ar ct="2505041405" l="29"/>
</s>


<s id="-5640385034831487405-2505041433-1" eva="8010101">
    <dp ct="2505041433" l="2"/>
</s>


<s id="3570813661258774062-2505041402-1" eva="8010101">
    <dp ct="2505041402" l="55"/>
</s>


<s id="7361217216108906343-2505041431-11" eva="8010101">
    <ar ct="2505041608" l="1"/>
    <dp ct="2505041611" l="1"/>
</s>


<s id="-3299300215104137566-2505042055-5" eva="8010101">
    <m id="r2414336" t="h" from="2505040615" to="2505050202" cat="Information" ts="2505040832" ts-tts="25-05-04 08:32:12.507" pr="3"/>
    <ar>
        <m id="r17210018" t="f" c="0" ts="2505041358" ts-tts="25-05-04 13:59:02.888"/>
    </ar>
    <dp>
        <m id="r17210018" t="f" c="0" ts="2505041358" ts-tts="25-05-04 13:59:02.888"/>
    </dp>
</s>


<s id="-10706323860843326-2505041026-19" eva="8010101">
    <ar ppth="Magdeburg Hbf|Magdeburg-Buckau|Schönebeck(Elbe)|Staßfurt|Güsten|Sandersleben(Anh)|Hettstedt|Klostermansfeld|Sangerhausen|Oberröblingen|Voigtstedt|Artern|Heldrungen|Griefstedt|Leubingen|Sömmerda|Großrudestedt|Stotternheim" cp="8" pp="5" ct="2505041359" pt="2505041250" l="RE10"/>
    <tl t="p" o="RSMD" c="SMD" n="74843"/>
</s>


<s id="-6880267813490232387-2505041219-16" eva="8010101">
    <ar ct="2505041358" l="44">
        <m id="r17209881" t="d" c="43" ts="2505041353" ts-tts="25-05-04 13:53:23.313"/>
    </ar>
</s>


<s id="-8619543569722847563-2505041208-8" eva="8010101">
    <ar ct="2505041352" l="1">
        <m id="r17207704" t="d" c="68" ts="2505041241" ts-tts="25-05-04 12:41:20.004"/>
        <m id="r17207709" t="q" c="92" ts="2505041241" ts-tts="25-05-04 12:41:35.436"/>
    </ar>
    <dp ct="2505041356" l="1">
        <m id="r17207704" t="d" c="68" ts="2505041241" ts-tts="25-05-04 12:41:20.004"/>
        <m id="r17207709" t="q" c="92" ts="2505041241" ts-tts="25-05-04 12:41:35.436"/>
    </dp>
</s>


<s id="1925161470190768333-2505041352-1" eva="8010101">
    <dp ct="2505041355" l="29"/>
</s>


<s id="390102360588381432-2505041234-11" eva="8010101">
    <ar ct="2505041351" l="55"/>
</s>


<s id="-4886039780563787696-2505041252-12" eva="8010101">
    <ar ct="2505041351" l="59"/>
</s>


<s id="-4503530441970809798-2505041419-9" eva="8010101">
    <m id="r2413050" t="h" from="2505011915" to="2505052359" cat="Information" ts="2505011920" ts-tts="25-05-03 23:16:03.739" pr="2"/>
    <ar ct="2505041828">
        <m id="r17199052" t="f" c="0" ts="2505040432" ts-tts="25-05-04 04:32:31.029"/>
        <m id="r17204653" t="f" c="0" ts="2505041051" ts-tts="25-05-04 10:51:57.861"/>
    </ar>
    <dp ct="2505041831">
        <m id="r17199052" t="f" c="0" ts="2505040432" ts-tts="25-05-04 04:32:31.029"/>
        <m id="r17204653" t="f" c="0" ts="2505041051" ts-tts="25-05-04 10:51:57.861"/>
    </dp>
</s>


<s id="-367631472485099277-2505040709-9" eva="8010101">
    <ar cpth="Frankfurt(Main)Süd|Fulda" ct="2505041346" l="10">
        <m id="r17190469" t="f" c="0" ts="2505032043" ts-tts="25-05-03 20:43:21.580"/>
        <m id="r17190470" t="f" c="1000" ts="2505032043" ts-tts="25-05-03 20:43:21.580"/>
        <m id="r17204211" t="f" c="0" ts="2505041033" ts-tts="25-05-04 10:33:27.631"/>
        <m id="r17204212" t="f" c="1000" ts="2505041033" ts-tts="25-05-04 10:33:27.631"/>
        <m id="r17205009" t="d" c="48" ts="2505041107" ts-tts="25-05-04 11:07:07.828"/>
        <m id="r17206180" t="d" c="48" ts="2505041146" ts-tts="25-05-04 11:47:00.979"/>
    </ar>
    <dp cpth="Halle(Saale)Hbf|Berlin Hbf" ct="2505041348" l="10">
        <m id="r17190469" t="f" c="0" ts="2505032043" ts-tts="25-05-03 20:43:21.580"/>
        <m id="r17190470" t="f" c="1000" ts="2505032043" ts-tts="25-05-03 20:43:21.580"/>
        <m id="r17204211" t="f" c="0" ts="2505041033" ts-tts="25-05-04 10:33:27.631"/>
        <m id="r17204212" t="f" c="1000" ts="2505041033" ts-tts="25-05-04 10:33:27.631"/>
        <m id="r17205009" t="d" c="48" ts="2505041107" ts-tts="25-05-04 11:07:07.828"/>
        <m id="r17206180" t="d" c="48" ts="2505041146" ts-tts="25-05-04 11:47:00.979"/>
    </dp>
</s>


<s id="-4234053143345121617-2505040950-8" eva="8010101">
    <m id="r2413050" t="h" from="2505011915" to="2505052359" cat="Information" ts="2505011920" ts-tts="25-05-03 23:16:03.740" pr="2"/>
    <ar ct="2505041344"/>
    <dp ct="2505041347"/>
</s>


<s id="2029820389210775089-2505041113-12" eva="8010101">
    <ar cpth="Eisenach Hbf|Wutha|Schönau(Hörsel)|Sättelstädt|Mechterstädt|Fröttstädt|Gotha|Seebergen|Wandersleben|Neudietendorf|Erfurt-Bischleben" ct="2505041159" l="20"/>
    <dp cpth="Vieselbach|Hopfgarten(Weimar)|Weimar|Oßmannstedt|Apolda|Niedertrebra|Bad Sulza|Großheringen|Bad Kösen|Naumburg(Saale)Hbf|Leißling|Weißenfels|Großkorbetha|Bad Dürrenberg|Kötzschau|Großlehna|Markranstädt|Leipzig-Miltitz|Leipzig-Rückmarsdorf|Leipzig-Leutzsch" ct="2505041204" l="20"/>
</s>


<s id="7074087403146415227-2505041413-11" eva="8010101">
    <m id="r2413050" t="h" from="2505011915" to="2505052359" cat="Information" ts="2505011920" ts-tts="25-05-03 23:16:03.739" pr="2"/>
    <ar cpth="Kiel Hbf|Neumünster|Hamburg-Altona|Hamburg Dammtor|Hamburg Hbf|Berlin-Spandau|Berlin Hbf|Berlin Südkreuz|Bitterfeld|Halle(Saale)Hbf" ct="2505041924">
        <m id="r17126116" t="f" c="0" ts="2505021217" ts-tts="25-05-02 12:17:28.116"/>
        <m id="r17159398" t="f" c="0" ts="2505030151" ts-tts="25-05-03 01:51:30.378"/>
    </ar>
    <dp cpth="Bamberg|Nürnberg Hbf|Donauwörth|Augsburg Hbf|München-Pasing|München Hbf" ct="2505041932">
        <m id="r17126116" t="f" c="0" ts="2505021217" ts-tts="25-05-02 12:17:28.116"/>
        <m id="r17159398" t="f" c="0" ts="2505030151" ts-tts="25-05-03 01:51:30.378"/>
    </dp>
</s>


<s id="-8500006782676143980-2505041338-1" eva="8010101">
    <dp ct="2505041338" l="23"/>
</s>


<s id="-5350699686138107641-2505041338-1" eva="8010101">
    <dp ct="2505041338" l="46"/>
</s>


<s id="-5225366604130971375-2505041408-8" eva="8010101">
    <ar ct="2505041546" l="1"/>
    <dp ct="2505041552" l="1"/>
</s>


<s id="6640210071275454214-2505041335-1" eva="8010101">
    <dp ct="2505041338" l="7">
        <m id="r17191637" t="f" c="0" ts="2505032119" ts-tts="25-05-03 21:20:02.860"/>
    </dp>
</s>


<s id="3569875999766897102-2505041738-1" eva="8010101">
    <m id="r2337696" t="h" from="2412191635" to="2512131642" cat="Information" ts="2412191417" ts-tts="25-05-03 23:16:03.425" pr="2"/>
    <dp ct="2505041738" l="23"/>
</s>


<s id="-4172035167486804185-2505041738-1" eva="8010101">
    <dp ct="2505041738" l="46"/>
</s>


<s id="-3313342237472696204-2505041410-5" eva="8010101">
    <ar ct="2505041615"/>
    <dp ct="2505041618"/>
</s>


<s id="8602607341575753545-2505041436-12" eva="8010101">
    <ar cp="8" ct="2505041529" l="20"/>
</s>


<s id="-8316478508966750425-2505041302-4" eva="8010101">
    <ar ct="2505041338" l="3"/>
</s>


<s id="4755851665441451528-2505041118-6" eva="8010101">
    <ar ct="2505041336">
        <m id="r17208327" t="f" c="0" ts="2505041301" ts-tts="25-05-04 13:01:54.602"/>
    </ar>
    <dp ct="2505041340">
        <m id="r17208327" t="f" c="0" ts="2505041301" ts-tts="25-05-04 13:01:54.602"/>
    </dp>
</s>


<s id="5503046623048511589-2505041333-1" eva="8010101">
    <dp cp="8a" ct="2505041334" l="16"/>
</s>


<s id="5755995936667922848-2505041327-1" eva="8010101">
    <dp cp="10" ct="2505041333" l="20">
        <m id="r17209164" t="d" c="47" ts="2505041334" ts-tts="25-05-04 13:34:04.390"/>
    </dp>
</s>


<s id="-4248001207429758177-2505041236-12" eva="8010101">
    <ar cp="8" ct="2505041329" l="20"/>
</s>


<s id="-5981141401498695982-2505041056-5" eva="8010101">
    <m id="r2413050" t="h" from="2505011915" to="2505052359" cat="Information" ts="2505011920" ts-tts="25-05-03 23:16:03.739" pr="2"/>
    <ar cp="9" ct="2505041329">
        <m id="r17204611" t="d" c="36" ts="2505041049" ts-tts="25-05-04 10:49:54.645"/>
        <m id="r17205537" t="f" c="0" ts="2505041126" ts-tts="25-05-04 11:26:25.134"/>
    </ar>
    <dp cp="9" ct="2505041331">
        <m id="r17204611" t="d" c="36" ts="2505041049" ts-tts="25-05-04 10:49:54.645"/>
        <m id="r17205537" t="f" c="0" ts="2505041126" ts-tts="25-05-04 11:26:25.134"/>
    </dp>
</s>


<s id="5266590292548768120-2505041126-5" eva="8010101">
    <ar ct="2505041331"/>
    <dp ct="2505041334"/>
</s>


<s id="-9171639706664093902-2505041527-1" eva="8010101">
    <dp cp="10" l="20"/>
</s>


<s id="4299006133984367960-2505041106-14" eva="8010101">
    <ar ct="2505041328" l="2"/>
</s>


<s id="7681615890422939097-2505041309-2" eva="8010101">
    <ar cp="10" ct="2505041328" l="16"/>
</s>


<s id="-5215562550739312304-2505041725-15" eva="8010101">
    <ar ct="2505041843" l="21"/>
</s>


<s id="-8750926457781455409-2505041204-7" eva="8010101">
    <m id="r2414420" t="h" from="2505041204" to="2505041500" cat="Information" ts="2505041208" ts-tts="25-05-04 12:08:22.558" pr="2"/>
    <ar ct="2505041322">
        <m id="r17206851" t="q" c="95" ts="2505041211" ts-tts="25-05-04 12:11:43.070"/>
    </ar>
    <dp ct="2505041325">
        <m id="r17206851" t="q" c="95" ts="2505041211" ts-tts="25-05-04 12:11:43.070"/>
    </dp>
</s>


<s id="8793213226106504000-2505040919-9" eva="8010101">
    <m id="r2297727" t="h" from="2412150000" to="2512132359" cat="Information" ts="2504111429" ts-tts="25-05-03 23:16:03.417" pr="2"/>
    <m id="r2413050" t="h" from="2505011915" to="2505052359" cat="Information" ts="2505011920" ts-tts="25-05-03 23:16:03.739" pr="2"/>
    <m id="r2414119" t="h" from="2505040505" to="2505050659" cat="Information" ts="2505040219" ts-tts="25-05-04 09:16:01.144" pr="3"/>
    <ar ct="2505041325"/>
    <dp ct="2505041332"/>
</s>


<s id="4628797216718709444-2505041353-5" eva="8010101">
    <m id="r2413050" t="h" from="2505011915" to="2505052359" cat="Information" ts="2505011920" ts-tts="25-05-03 23:16:03.739" pr="2"/>
    <ar ct="2505041624"/>
    <dp ct="2505041632"/>
</s>


<s id="-5804428351779687327-2505041128-4" eva="8010101">
    <ar ct="2505041319" l="10">
        <m id="r17190757" t="f" c="0" ts="2505032049" ts-tts="25-05-03 20:49:34.447"/>
        <m id="r17190758" t="f" c="1000" ts="2505032049" ts-tts="25-05-03 20:49:34.447"/>
    </ar>
    <dp ct="2505041321" l="10">
        <m id="r17190757" t="f" c="0" ts="2505032049" ts-tts="25-05-03 20:49:34.447"/>
        <m id="r17190758" t="f" c="1000" ts="2505032049" ts-tts="25-05-03 20:49:34.447"/>
    </dp>
</s>


<s id="-6137889975867506599-2505041051-3" eva="8010101">
    <ar ct="2505041317">
        <m id="r17207001" t="d" c="67" ts="2505041217" ts-tts="25-05-04 12:17:23.671"/>
    </ar>
    <dp ct="2505041321">
        <m id="r17207001" t="d" c="67" ts="2505041217" ts-tts="25-05-04 12:17:23.671"/>
    </dp>
</s>


<s id="-8750803673781214551-2505041204-7" eva="8010101">
    <ar ct="2505041322" l="51">
        <m id="r17206852" t="q" c="95" ts="2505041211" ts-tts="25-05-04 12:11:43.069"/>
    </ar>
</s>


<s id="7266894607367418061-2505041109-23" eva="8010101">
    <ar ct="2505041315" l="20">
        <m id="r17206024" t="d" c="48" ts="2505041142" ts-tts="25-05-04 11:42:23.211"/>
    </ar>
    <dp ct="2505041318" l="20">
        <m id="r17206024" t="d" c="48" ts="2505041142" ts-tts="25-05-04 11:42:23.211"/>
    </dp>
</s>


<s id="6270968194640810761-2505041317-1" eva="8010101">
    <dp ct="2505041318" l="21"/>
</s>


<s id="-9028005792529481477-2505041056-7" eva="8010101">
    <ar ct="2505041519" l="10">
        <m id="r17190670" t="f" c="0" ts="2505032047" ts-tts="25-05-03 20:47:14.360"/>
        <m id="r17190671" t="f" c="1000" ts="2505032047" ts-tts="25-05-03 20:47:29.884"/>
        <m id="r17190679" t="f" c="0" ts="2505032047" ts-tts="25-05-03 20:47:45.382"/>
    </ar>
    <dp ct="2505041522" l="10">
        <m id="r17190670" t="f" c="0" ts="2505032047" ts-tts="25-05-03 20:47:14.360"/>
        <m id="r17190671" t="f" c="1000" ts="2505032047" ts-tts="25-05-03 20:47:29.884"/>
        <m id="r17190679" t="f" c="0" ts="2505032047" ts-tts="25-05-03 20:47:45.382"/>
    </dp>
</s>


<s id="4835543134229700432-2505041716-1" eva="8010101">
    <dp ct="2505041716" l="21"/>
</s>


<s id="-7175538114342418409-2505041212-14" eva="8010101">
    <ar ct="2505041318" l="23"/>
</s>


<s id="-2906500349579796599-2505041218-14" eva="8010101">
    <ar ct="2505041318" l="46"/>
</s>


<s id="-3115913713528358315-2505040725-1" eva="8010101">
    <m id="r2414447" t="h" from="2505040725" to="2505041435" cat="Information" ts="2505041316" ts-tts="25-05-04 13:16:19.613" pr="2"/>
    <dp cp="1" ct="2505040725"/>
</s>


<s id="2662972692212507122-2505050506-8" eva="8010101">
    <ar cpth="München Hbf|München-Pasing|Augsburg Hbf|Donauwörth|Treuchtlingen|Nürnberg Hbf|Bamberg">
        <m id="r17169944" t="f" c="0" ts="2505031126" ts-tts="25-05-03 11:26:12.548"/>
        <m id="r17198039" t="f" c="0" ts="2505040151" ts-tts="25-05-04 01:51:13.312"/>
    </ar>
    <dp cpth="Halle(Saale)Hbf|Bitterfeld|Berlin Südkreuz|Berlin Hbf|Berlin-Spandau|Hamburg Hbf|Hamburg-Altona|Neumünster|Kiel Hbf">
        <m id="r17169944" t="f" c="0" ts="2505031126" ts-tts="25-05-03 11:26:12.548"/>
        <m id="r17198039" t="f" c="0" ts="2505040151" ts-tts="25-05-04 01:51:13.312"/>
    </dp>
</s>


<s id="-8690284524071151397-2505041712-13" eva="8010101">
    <ar ct="2505041817" l="23"/>
</s>


<s id="-9195590069004936627-2505041102-2" eva="8010101">
    <ar ct="2505041308">
        <m id="r17206171" t="q" c="97" ts="2505041146" ts-tts="25-05-04 11:46:45.553"/>
        <m id="r17206948" t="q" c="97" ts="2505041215" ts-tts="25-05-04 12:15:34.503"/>
    </ar>
    <dp ct="2505041311">
        <m id="r17206171" t="q" c="97" ts="2505041146" ts-tts="25-05-04 11:46:45.553"/>
        <m id="r17206948" t="q" c="97" ts="2505041215" ts-tts="25-05-04 12:15:34.503"/>
    </dp>
</s>


<s id="2636233896290798975-2505041452-12" eva="8010101">
    <ar ct="2505041551" l="59"/>
</s>


<s id="-5791504741730244841-2505041307-1" eva="8010101">
    <dp ct="2505041307" l="52"/>
</s>


<s id="4083739950560377043-2505041028-8" eva="8010101">
    <ar ct="2505041826">
        <m id="r17204934" t="d" c="43" ts="2505041104" ts-tts="25-05-04 11:04:17.921"/>
    </ar>
    <dp ct="2505041828">
        <m id="r17204934" t="d" c="43" ts="2505041104" ts-tts="25-05-04 11:04:17.921"/>
    </dp>
</s>


<s id="-5710193971307432213-2505041206-12" eva="8010101">
    <ar cp="8a" ct="2505041256" l="20">
        <m id="r17206893" t="d" c="43" ts="2505041213" ts-tts="25-05-04 12:13:46.520"/>
    </ar>
    <dp cp="8a" ct="2505041304" l="20">
        <m id="r17206893" t="d" c="43" ts="2505041213" ts-tts="25-05-04 12:13:46.520"/>
    </dp>
</s>


<s id="-1657023877923402012-2505041302-1" eva="8010101">
    <dp ct="2505041303" l="56"/>
</s>


<s id="-502444458290614507-2505041329-16" eva="8010101">
    <ar ct="2505041456" l="56">
        <m id="r17198877" t="q" c="93" ts="2505040340" ts-tts="25-05-04 03:40:33.684"/>
    </ar>
</s>


<s id="8379187795795167441-2505041046-5" eva="8010101">
    <m id="r2414390" t="h" from="2505041046" to="2505041508" cat="Information" ts="2505041113" ts-tts="25-05-04 11:13:33.264" pr="2"/>
    <ar ct="2505041256">
        <m id="r17204957" t="f" c="0" ts="2505041105" ts-tts="25-05-04 11:05:19.634"/>
        <m id="r17204983" t="d" c="36" ts="2505041106" ts-tts="25-05-04 11:06:21.498"/>
    </ar>
    <dp ct="2505041257">
        <m id="r17204957" t="f" c="0" ts="2505041105" ts-tts="25-05-04 11:05:19.634"/>
        <m id="r17204983" t="d" c="36" ts="2505041106" ts-tts="25-05-04 11:06:21.498"/>
    </dp>
</s>


<s id="1382060687281793147-2505041129-16" eva="8010101">
    <ar ct="2505041256" l="56"/>
</s>


<s id="-7459823331390406091-2505041323-3" eva="8010101">
    <ar cpth="Berlin Hbf|Halle(Saale)Hbf" ct="2505041517" l="10">
        <m id="r17190497" t="f" c="0" ts="2505032043" ts-tts="25-05-03 20:43:52.574"/>
        <m id="r17190498" t="f" c="1000" ts="2505032043" ts-tts="25-05-03 20:43:52.574"/>
    </ar>
    <dp cpth="Fulda|Frankfurt(Main)Süd|Mannheim Hbf|Karlsruhe Hbf" ct="2505041520" l="10">
        <m id="r17190497" t="f" c="0" ts="2505032043" ts-tts="25-05-03 20:43:52.574"/>
        <m id="r17190498" t="f" c="1000" ts="2505032043" ts-tts="25-05-03 20:43:52.574"/>
    </dp>
</s>


<s id="-2012686948782912427-2505041513-7" eva="8010101">
    <ar>
        <m id="r17208035" t="f" c="0" ts="2505041253" ts-tts="25-05-04 12:53:40.970"/>
    </ar>
    <dp>
        <m id="r17208035" t="f" c="0" ts="2505041253" ts-tts="25-05-04 12:53:40.970"/>
    </dp>
</s>


<s id="8934521651957772737-2505041250-1" eva="8010101">
    <dp ct="2505041250" l="3"/>
</s>


<s id="1621442479220822598-2505041250-1" eva="8010101">
    <dp ct="2505041250" l="3"/>
</s>


<s id="-2365943148004192003-2505041319-18" eva="8010101">
    <ar ct="2505041446" l="52">
        <m id="r17198902" t="q" c="93" ts="2505040342" ts-tts="25-05-04 03:42:51.221"/>
    </ar>
</s>


<s id="8595060505597233374-2505041318-6" eva="8010101">
    <ar ct="2505041536"/>
    <dp ct="2505041540"/>
</s>


<s id="-7894185240135079180-2505041318-9" eva="8010101">
    <m id="r2413050" t="h" from="2505011915" to="2505052359" cat="Information" ts="2505011920" ts-tts="25-05-03 23:16:03.739" pr="2"/>
    <ar ct="2505041724"/>
    <dp ct="2505041732"/>
</s>


<s id="-45684134683608942-2505041051-5" eva="8010101">
    <ar ct="2505041244"/>
    <dp ct="2505041247"/>
</s>


<s id="7126410589925001885-2505041119-18" eva="8010101">
    <ar ct="2505041246" l="52"/>
</s>


<s id="277583807478221177-2505041643-18" eva="8010101">
    <ar ct="2505041817" l="46"/>
</s>


<s id="-6595250347505209288-2505041125-15" eva="8010101">
    <ar ct="2505041244" l="21"/>
</s>


<s id="9068686775942580608-2505041238-1" eva="8010101">
    <dp ct="2505041239" l="46"/>
</s>


<s id="-1445671294878124782-2505041238-1" eva="8010101">
    <dp ct="2505041239" l="23"/>
</s>


<s id="-7213340874059439574-2505041638-1" eva="8010101">
    <dp ct="2505041638" l="23"/>
</s>


<s id="-5946610016611470999-2505041638-1" eva="8010101">
    <dp ct="2505041638" l="46"/>
</s>


<s id="7143351838235944095-2505041235-1" eva="8010101">
    <dp ct="2505041236" l="16"/>
</s>


<s id="-690776802853422910-2505040440-9" eva="8010101">
    <m id="r2297280" t="h" from="2412150000" to="2512132359" cat="Information" ts="2504111409" ts-tts="25-05-03 23:16:03.417" pr="2"/>
    <ar ct="2505041232">
        <m id="r17199652" t="d" c="31" ts="2505040617" ts-tts="25-05-04 06:17:53.068"/>
        <m id="r17201493" t="f" c="0" ts="2505040822" ts-tts="25-05-04 08:22:27.088"/>
        <m id="r17205362" t="f" c="0" ts="2505041120" ts-tts="25-05-04 11:20:29.718"/>
    </ar>
    <dp ct="2505041234">
        <m id="r17199652" t="d" c="31" ts="2505040617" ts-tts="25-05-04 06:17:53.068"/>
        <m id="r17201493" t="f" c="0" ts="2505040822" ts-tts="25-05-04 08:22:27.088"/>
        <m id="r17205362" t="f" c="0" ts="2505041120" ts-tts="25-05-04 11:20:29.718"/>
    </dp>
</s>


<s id="1778405555935277912-2505041233-1" eva="8010101">
    <dp ct="2505041233" l="2"/>
</s>


<s id="-2467281444360141068-2505040818-9" eva="8010101">
    <m id="r2413050" t="h" from="2505011915" to="2505052359" cat="Information" ts="2505011920" ts-tts="25-05-03 23:16:03.739" pr="2"/>
    <ar ct="2505041229">
        <m id="r17202686" t="f" c="0" ts="2505040926" ts-tts="25-05-04 09:26:38.701"/>
        <m id="r17203065" t="f" c="0" ts="2505040943" ts-tts="25-05-04 09:43:36.105"/>
    </ar>
    <dp ct="2505041232">
        <m id="r17202686" t="f" c="0" ts="2505040926" ts-tts="25-05-04 09:26:38.701"/>
        <m id="r17203065" t="f" c="0" ts="2505040943" ts-tts="25-05-04 09:43:36.105"/>
    </dp>
</s>


<s id="2342573116787471412-2505040838-7" eva="8010101">
    <m id="r2414432" t="h" from="2505040613" to="2505041353" cat="Information" ts="2505041229" ts-tts="25-05-04 12:29:44.639" pr="2"/>
    <ar cp="2" ct="2505041206"/>
    <dp cp="2" ct="2505041210"/>
</s>


<s id="-6539604507256114562-2505040613-10" eva="8010101">
    <m id="r2413954" t="h" from="2505031530" to="2505050000" cat="Störung" ts="2505031627" ts-tts="25-05-04 10:16:00.962" pr="1"/>
    <m id="r2414432" t="h" from="2505040613" to="2505041353" cat="Information" ts="2505041229" ts-tts="25-05-04 12:29:44.639" pr="2"/>
    <ar cpth="Wien Hbf|Wien Meidling|St.Pölten Hbf|Linz Hbf|Wels Hbf|Passau Hbf|Regensburg Hbf|Nürnberg Hbf|Coburg" cp="2" ct="2505041206">
        <m id="r17194822" t="f" c="0" ts="2505032339" ts-tts="25-05-03 23:39:11.192"/>
    </ar>
    <dp cpth="Halle(Saale)Hbf|Berlin Südkreuz|Berlin Hbf|Berlin-Spandau|Hamburg Hbf|Hamburg-Altona" cp="2" ct="2505041208">
        <m id="r17194822" t="f" c="0" ts="2505032339" ts-tts="25-05-03 23:39:11.192"/>
    </dp>
</s>


<s id="-344974020920810328-2505041202-3" eva="8010101">
    <ar ct="2505041227" l="16"/>
</s>


<s id="3657993984016871147-2505040954-5" eva="8010101">
    <m id="r2413050" t="h" from="2505011915" to="2505052359" cat="Information" ts="2505011920" ts-tts="25-05-03 23:16:03.739" pr="2"/>
    <ar ct="2505041223"/>
    <dp ct="2505041232"/>
</s>


<s id="5717105397591316153-2505041220-1" eva="8010101">
    <dp ct="2505041220" l="3"/>
</s>


<s id="-2528742389814469794-2505041619-16" eva="8010101">
    <ar ct="2505041751" l="44"/>
</s>


<s id="-1386963014845247043-2505041001-13" eva="8010101">
    <ar ct="2505041220" l="7"/>
</s>


<s id="-1846256534472460947-2505041618-14" eva="8010101">
    <ar ct="2505041717" l="46"/>
</s>


<s id="5241093095753012962-2505041043-18" eva="8010101">
    <ar ct="2505041217" l="46"/>
</s>


<s id="-4892589473570259708-2505041112-13" eva="8010101">
    <ar ct="2505041217" l="23"/>
</s>


<s id="1081377433646804832-2505041612-14" eva="8010101">
    <ar ct="2505041717" l="23"/>
</s>


<s id="5656583513138578556-2505041010-5" eva="8010101">
    <ar ct="2505041212"/>
    <dp ct="2505041218"/>
</s>


<s id="5273690909914691752-2505041031-11" eva="8010101">
    <ar ct="2505041207" l="1"/>
    <dp ct="2505041210" l="1"/>
</s>


<s id="-2000898735252103255-2505041209-1" eva="8010101">
    <dp ct="2505041209" l="59"/>
</s>


<s id="766778547795655952-2505041605-1" eva="8010101">
    <dp ct="2505041605" l="44"/>
</s>


<s id="-1867468303541317334-2505041205-1" eva="8010101">
    <dp ct="2505041205" l="44"/>
</s>


<s id="-3822546903242959347-2505041202-1" eva="8010101">
    <dp ct="2505041202" l="55">
        <m id="r17198869" t="q" c="93" ts="2505040339" ts-tts="25-05-04 03:39:47.703"/>
    </dp>
</s>


<s id="616222733203194222-2505041009-23" eva="8010101">
    <ar ct="2505041158" l="20"/>
    <dp ct="2505041201" l="20"/>
</s>


<s id="-7749948440523977195-2505041019-16" eva="8010101">
    <ar ct="2505041152" l="44"/>
</s>


<s id="8255724909315155820-2505041034-11" eva="8010101">
    <ar ct="2505041151" l="55">
        <m id="r17198865" t="q" c="93" ts="2505040339" ts-tts="25-05-04 03:39:32.448"/>
    </ar>
</s>


<s id="552350461142098439-2505041052-12" eva="8010101">
    <ar ct="2505041151" l="59"/>
</s>


<s id="-6613161538024503824-2505040751-7" eva="8010101">
    <m id="r2413950" t="h" from="2505031530" to="2505050000" cat="Störung" ts="2505031622" ts-tts="25-05-04 10:16:00.962" pr="1"/>
    <ar ct="2505041149"/>
    <dp ct="2505041154"/>
</s>


<s id="2404626699059930299-2505041008-8" eva="8010101">
    <ar ct="2505041147" l="1"/>
    <dp ct="2505041153" l="1"/>
</s>


<s id="5587501995840217860-2505040854-4" eva="8010101">
    <ar ct="2505041137">
        <m id="r17204231" t="d" c="43" ts="2505041033" ts-tts="25-05-04 10:33:58.454"/>
        <m id="r17205165" t="d" c="55" ts="2505041113" ts-tts="25-05-04 11:14:04.159"/>
    </ar>
    <dp ct="2505041138">
        <m id="r17204231" t="d" c="43" ts="2505041033" ts-tts="25-05-04 10:33:58.454"/>
        <m id="r17205165" t="d" c="55" ts="2505041113" ts-tts="25-05-04 11:14:04.159"/>
    </dp>
</s>


<s id="-258190736644100419-2505040854-4" eva="8010101">
    <m id="r2413050" t="h" from="2505011915" to="2505052359" cat="Information" ts="2505011920" ts-tts="25-05-03 23:16:03.739" pr="2"/>
    <ar ct="2505041137">
        <m id="r17202276" t="f" c="0" ts="2505040909" ts-tts="25-05-04 09:09:57.241"/>
        <m id="r17204230" t="d" c="43" ts="2505041033" ts-tts="25-05-04 10:33:58.454"/>
        <m id="r17205163" t="d" c="55" ts="2505041113" ts-tts="25-05-04 11:14:04.159"/>
    </ar>
    <dp ct="2505041138">
        <m id="r17202276" t="f" c="0" ts="2505040909" ts-tts="25-05-04 09:09:57.241"/>
        <m id="r17204230" t="d" c="43" ts="2505041033" ts-tts="25-05-04 10:33:58.454"/>
        <m id="r17205163" t="d" c="55" ts="2505041113" ts-tts="25-05-04 11:14:04.159"/>
    </dp>
</s>


<s id="-4683407177912444071-2505041138-1" eva="8010101">
    <dp ct="2505041138" l="46"/>
</s>


<s id="-8081092753543241869-2505041538-1" eva="8010101">
    <dp ct="2505041538" l="23"/>
</s>


<s id="-7211057419839904967-2505041138-1" eva="8010101">
    <dp ct="2505041138" l="23"/>
</s>


<s id="-1029020035955594699-2505041538-1" eva="8010101">
    <dp ct="2505041538" l="46"/>
</s>


<s id="-8746753259750064839-2505041135-1" eva="8010101">
    <dp ct="2505041138" l="7">
        <m id="r17190476" t="f" c="0" ts="2505032043" ts-tts="25-05-03 20:43:37.090"/>
    </dp>
</s>


<s id="7807335753361610506-2505041102-4" eva="8010101">
    <ar ct="2505041137" l="3"/>
</s>


<s id="251575652045242657-2505040918-6" eva="8010101">
    <ar ct="2505041135"/>
    <dp ct="2505041140"/>
</s>


<s id="-8532538561908887406-2505041131-1" eva="8010101">
    <dp ct="2505041132" l="16"/>
</s>


<s id="5254114651454294172-2505040916-6" eva="8010101">
    <m id="r2413074" t="h" from="2505041901" to="2505041903" cat="Großstörung" ts="2505032303" ts-tts="25-05-03 23:03:55.989" pr="1"/>
    <ar ct="2505041129"/>
    <dp ct="2505041132"/>
</s>


<s id="-795470299631124600-2505041027-9" eva="8010101">
    <ar ct="2505041644">
        <m id="r17205693" t="d" c="43" ts="2505041131" ts-tts="25-05-04 11:32:05.300"/>
    </ar>
    <dp ct="2505041647">
        <m id="r17205693" t="d" c="43" ts="2505041131" ts-tts="25-05-04 11:32:05.300"/>
    </dp>
</s>


<s id="9131128110337069714-2505041127-1" eva="8010101">
    <dp cp="8a" ct="2505041127" l="20"/>
</s>


<s id="5461023084946911171-2505041525-15" eva="8010101">
    <ar ct="2505041643" l="21"/>
</s>


<s id="5407425180793604595-2505041109-2" eva="8010101">
    <ar cp="8a" ct="2505041123" l="16"/>
</s>


<s id="-1036339123872447767-2505040650-7" eva="8010101">
    <ar ct="2505041120" l="10">
        <m id="r17190601" t="f" c="0" ts="2505032046" ts-tts="25-05-03 20:46:43.334"/>
        <m id="r17190603" t="f" c="1000" ts="2505032046" ts-tts="25-05-03 20:46:43.334"/>
    </ar>
    <dp ct="2505041122" l="10">
        <m id="r17186467" t="f" c="1000" ts="2505031900" ts-tts="25-05-03 19:00:42.888"/>
        <m id="r17190601" t="f" c="0" ts="2505032046" ts-tts="25-05-03 20:46:43.334"/>
        <m id="r17190602" t="f" c="1000" ts="2505032046" ts-tts="25-05-03 20:46:43.334"/>
    </dp>
</s>


<s id="-7834905235620477087-2505040906-14" eva="8010101">
    <ar ct="2505041122" l="2"/>
</s>


<s id="3633423506968040756-2505040718-9" eva="8010101">
    <m id="r2414097" t="h" from="2505040718" to="2505050001" cat="Information" ts="2505040018" ts-tts="25-05-04 00:18:58.392" pr="2"/>
    <m id="r2413050" t="h" from="2505011915" to="2505052359" cat="Information" ts="2505011920" ts-tts="25-05-03 23:16:03.739" pr="2"/>
    <ar ct="2505041121">
        <m id="r17200947" t="d" c="44" ts="2505040745" ts-tts="25-05-04 07:45:43.859"/>
    </ar>
    <dp ct="2505041132">
        <m id="r17200947" t="d" c="44" ts="2505040745" ts-tts="25-05-04 07:45:43.859"/>
    </dp>
</s>


<s id="-2107858648418212462-2505041517-1" eva="8010101">
    <dp ct="2505041517" l="21"/>
</s>


<s id="-3548203338926394721-2505041116-1" eva="8010101">
    <dp ct="2505041117" l="21"/>
</s>


<s id="2369074087942045549-2505041018-14" eva="8010101">
    <ar ct="2505041117" l="46"/>
</s>


<s id="-7206254836692319443-2505041012-14" eva="8010101">
    <ar ct="2505041117" l="23"/>
</s>


<s id="-2237893848616905433-2505040851-3" eva="8010101">
    <ar ct="2505041109">
        <m id="r17204086" t="f" c="0" ts="2505041028" ts-tts="25-05-04 10:28:50.288"/>
    </ar>
    <dp ct="2505041113">
        <m id="r17204086" t="f" c="0" ts="2505041028" ts-tts="25-05-04 10:28:50.288"/>
    </dp>
</s>


<s id="-6118354941572328678-2505041512-13" eva="8010101">
    <ar ct="2505041617" l="23"/>
</s>


<s id="1786355638125418713-2505040628-9" eva="8010101">
    <m id="r2361630" t="h" from="2504120628" to="2505251700" cat="Bauarbeiten" ts="2504112302" ts-tts="25-05-03 23:16:03.428" pr="1"/>
    <m id="r2361631" t="h" from="2504120628" to="2505251700" cat="Bauarbeiten" ts="2504112302" ts-tts="25-05-03 23:16:03.428" pr="1"/>
    <m id="r2361632" t="h" from="2504120628" to="2505251700" cat="Bauarbeiten" ts="2504112302" ts-tts="25-05-03 23:16:03.428" pr="1"/>
    <m id="r2361786" t="h" from="2504120628" to="2505251700" cat="Bauarbeiten" ts="2504112302" ts-tts="25-05-03 23:16:03.428" pr="2"/>
    <m id="r2361629" t="h" from="2504120628" to="2505251700" cat="Bauarbeiten" ts="2504112302" ts-tts="25-05-03 23:16:03.428" pr="1"/>
    <m id="r2361633" t="h" from="2504120628" to="2505251700" cat="Bauarbeiten" ts="2504112302" ts-tts="25-05-03 23:16:03.428" pr="1"/>
    <m id="r2361634" t="h" from="2504120628" to="2505251700" cat="Bauarbeiten" ts="2504112302" ts-tts="25-05-03 23:16:03.428" pr="1"/>
    <m id="r2361635" t="h" from="2504120628" to="2505251700" cat="Bauarbeiten" ts="2504112302" ts-tts="25-05-03 23:16:03.428" pr="1"/>
    <ar ct="2505041108">
        <m id="r17200180" t="d" c="43" ts="2505040657" ts-tts="25-05-04 06:57:16.537"/>
    </ar>
    <dp ct="2505041111">
        <m id="r17200180" t="d" c="43" ts="2505040657" ts-tts="25-05-04 06:57:16.537"/>
    </dp>
</s>


<s id="-8442299977626677408-2505041110-1" eva="8010101">
    <dp ct="2505041110" l="RE10"/>
</s>


<s id="-7639581173675497315-2505041107-1" eva="8010101">
    <dp ct="2505041107" l="52">
        <m id="r17198900" t="q" c="93" ts="2505040342" ts-tts="25-05-04 03:42:35.967"/>
    </dp>
</s>


<s id="-1805497594174998570-2505040923-13" eva="8010101">
    <ar ct="2505041109" l="3"/>
</s>


<s id="-6785778272130955005-2505040909-23" eva="8010101">
    <ar ct="2505041055" l="20"/>
    <dp ct="2505041105" l="20"/>
</s>


<s id="5127549506780834051-2505041006-12" eva="8010101">
    <ar ct="2505041053" l="20"/>
    <dp ct="2505041104" l="20"/>
</s>


<s id="-802900883264379200-2505041102-1" eva="8010101">
    <dp ct="2505041102" l="56"/>
</s>


<s id="3992319517280243604-2505040904-4" eva="8010101">
    <ar ct="2505041058"/>
    <dp ct="2505041101"/>
</s>


<s id="907032525501751695-2505040929-16" eva="8010101">
    <ar ct="2505041056" l="56"/>
</s>


<s id="8090619804583308973-2505041050-1" eva="8010101">
    <dp ct="2505041050" l="3"/>
</s>


<s id="5491520693020023629-2505041050-1" eva="8010101">
    <dp ct="2505041050" l="3"/>
</s>


<s id="691295195574581439-2505040826-19" eva="8010101">
    <ar ct="2505041050" l="RE10"/>
</s>


<s id="2544998982356218950-2505040900-4" eva="8010101">
    <ar ct="2505041044"/>
    <dp ct="2505041047"/>
</s>


<s id="4997993580001785246-2505040919-18" eva="8010101">
    <ar ct="2505041045" l="52">
        <m id="r17190918" t="f" c="0" ts="2505032054" ts-tts="25-05-03 20:54:13.586"/>
        <m id="r17198896" t="q" c="93" ts="2505040342" ts-tts="25-05-04 03:42:20.671"/>
    </ar>
</s>


<s id="182196087643494312-2505041443-18" eva="8010101">
    <ar ct="2505041617" l="46"/>
</s>


<s id="-1228694128225925239-2505040925-15" eva="8010101">
    <ar ct="2505041043" l="21"/>
</s>


<s id="7655031270987755254-2505041038-1" eva="8010101">
    <dp ct="2505041038" l="46"/>
</s>


<s id="1446871442007218363-2505041038-1" eva="8010101">
    <dp ct="2505041038" l="23"/>
</s>


<s id="2167743840256423242-2505041438-1" eva="8010101">
    <dp ct="2505041438" l="46"/>
</s>


<s id="1578303357513069311-2505041438-1" eva="8010101">
    <dp ct="2505041438" l="23"/>
</s>


<s id="-1416348256231496225-2505041035-1" eva="8010101">
    <dp ct="2505041035" l="16"/>
</s>


<s id="-6146220678961140226-2505041033-1" eva="8010101">
    <dp ct="2505041033" l="2"/>
</s>


<s id="-3994803738459763974-2505040605-6" eva="8010101">
    <ar ct="2505041025">
        <m id="r17200261" t="d" c="43" ts="2505040703" ts-tts="25-05-04 07:04:11.037"/>
        <m id="r17200753" t="f" c="0" ts="2505040730" ts-tts="25-05-04 07:30:35.621"/>
    </ar>
    <dp ct="2505041029">
        <m id="r17200261" t="d" c="43" ts="2505040703" ts-tts="25-05-04 07:04:11.037"/>
        <m id="r17200753" t="f" c="0" ts="2505040730" ts-tts="25-05-04 07:30:35.621"/>
    </dp>
</s>


<s id="2451247525812680010-2505041002-3" eva="8010101">
    <ar ct="2505041026" l="16"/>
</s>


<s id="6722706556573355864-2505040713-7" eva="8010101">
    <m id="r2413050" t="h" from="2505011915" to="2505052359" cat="Information" ts="2505011920" ts-tts="25-05-03 23:16:03.739" pr="2"/>
    <m id="r2414218" t="h" from="2505040713" to="2505041438" cat="Information" ts="2505040710" ts-tts="25-05-04 07:10:20.286" pr="3"/>
    <ar ct="2505041024">
        <m id="r17199014" t="f" c="0" ts="2505040413" ts-tts="25-05-04 04:13:08.908"/>
        <m id="r17200477" t="q" c="95" ts="2505040717" ts-tts="25-05-04 07:17:15.720"/>
    </ar>
    <dp ct="2505041032">
        <m id="r17199014" t="f" c="0" ts="2505040413" ts-tts="25-05-04 04:13:08.908"/>
        <m id="r17200477" t="q" c="95" ts="2505040717" ts-tts="25-05-04 07:17:15.720"/>
    </dp>
</s>


<s id="-3783829201967449571-2505040617-9" eva="8010101">
    <m id="r2413050" t="h" from="2505011915" to="2505052359" cat="Information" ts="2505011920" ts-tts="25-05-03 23:16:03.739" pr="2"/>
    <ar ct="2505041023"/>
    <dp ct="2505041031"/>
</s>


<s id="7324466699652377369-2505041419-16" eva="8010101">
    <ar ct="2505041551" l="44"/>
</s>


<s id="9145020881380014050-2505040810-5" eva="8010101">
    <ar ct="2505041015"/>
    <dp ct="2505041018"/>
</s>


<s id="4077657699786612489-2505041418-14" eva="8010101">
    <ar ct="2505041517" l="46"/>
</s>


<s id="2094622953808785096-2505040912-13" eva="8010101">
    <ar ct="2505041019" l="23"/>
</s>


<s id="-4651634539935731235-2505040918-14" eva="8010101">
    <ar ct="2505041019" l="46"/>
</s>


<s id="-6902514329963894173-2505040831-11" eva="8010101">
    <ar ct="2505041011" l="1">
        <m id="r17190503" t="f" c="0" ts="2505032043" ts-tts="25-05-03 20:44:08.061"/>
        <m id="r17191599" t="f" c="0" ts="2505032118" ts-tts="25-05-03 21:19:00.595"/>
    </ar>
    <dp ct="2505041015" l="1">
        <m id="r17190503" t="f" c="0" ts="2505032043" ts-tts="25-05-03 20:44:08.061"/>
        <m id="r17191599" t="f" c="0" ts="2505032118" ts-tts="25-05-03 21:19:00.595"/>
    </dp>
</s>


<s id="6688954933111015014-2505041009-1" eva="8010101">
    <dp ct="2505041012" l="59"/>
</s>


<s id="52746391378738708-2505040810-9" eva="8010101">
    <ar ct="2505041004" l="29"/>
</s>


<s id="2177020880275303826-2505041005-1" eva="8010101">
    <dp ct="2505041006" l="44"/>
</s>


<s id="-6673977112586651688-2505040913-12" eva="8010101">
    <ar ct="2505040959" l="20"/>
    <dp ct="2505041004" l="20"/>
</s>


<s id="-3242064568636021121-2505041002-1" eva="8010101">
    <dp ct="2505041002" l="55"/>
</s>


<s id="-3437302050396324385-2505040809-23" eva="8010101">
    <ar ct="2505040955" l="20"/>
    <dp ct="2505041001" l="20"/>
</s>


<s id="8521135025264102349-2505040952-1" eva="8010101">
    <dp ct="2505040952" l="29"/>
</s>


<s id="-1427216182129917112-2505040819-16" eva="8010101">
    <ar ct="2505040951" l="44"/>
</s>


<s id="-1705942612133133008-2505040852-12" eva="8010101">
    <ar ct="2505040951" l="59"/>
</s>


<s id="4744567974114992676-2505040834-11" eva="8010101">
    <ar ct="2505040950" l="55"/>
</s>


<s id="5112591979346353004-2505040808-8" eva="8010101">
    <ar ct="2505040945" l="1"/>
    <dp ct="2505040952" l="1"/>
</s>


<s id="1334679016662297641-2505040801-13" eva="8010101">
    <ar ct="2505041020" l="7">
        <m id="r17202293" t="f" c="0" ts="2505040910" ts-tts="25-05-04 09:10:43.412"/>
        <m id="r17202294" t="f" c="1000" ts="2505040910" ts-tts="25-05-04 09:10:43.412"/>
        <m id="r17202296" t="q" c="92" ts="2505040910" ts-tts="25-05-04 09:10:43.412"/>
        <m id="r17203071" t="d" c="68" ts="2505040943" ts-tts="25-05-04 09:43:51.529"/>
    </ar>
</s>


<s id="7082061920494556007-2505040919-13" eva="8010101">
    <m id="r2414360" t="h" from="2505040915" to="2505041000" cat="Störung" ts="2505040943" ts-tts="25-05-04 09:43:20.576" pr="2"/>
    <ar cpth="" cs="c" clt="2505030151">
        <m id="r17125142" t="f" c="0" ts="2505021200" ts-tts="25-05-02 12:00:33.305"/>
        <m id="r17125247" t="d" c="31" ts="2505021201" ts-tts="25-05-02 12:01:04.512"/>
        <m id="r17155112" t="d" c="31" ts="2505022252" ts-tts="25-05-02 22:53:00.958"/>
        <m id="r17159354" t="f" c="0" ts="2505030151" ts-tts="25-05-03 01:51:30.379"/>
        <m id="r17159361" t="d" c="31" ts="2505030151" ts-tts="25-05-03 01:51:30.379"/>
        <m id="r17159859" t="d" c="31" ts="2505030152" ts-tts="25-05-03 01:52:47.256"/>
    </ar>
    <dp cpth="" cs="c" clt="2505030151">
        <m id="r17125142" t="f" c="0" ts="2505021200" ts-tts="25-05-02 12:00:33.305"/>
        <m id="r17125247" t="d" c="31" ts="2505021201" ts-tts="25-05-02 12:01:04.512"/>
        <m id="r17155112" t="d" c="31" ts="2505022252" ts-tts="25-05-02 22:53:00.958"/>
        <m id="r17159354" t="f" c="0" ts="2505030151" ts-tts="25-05-03 01:51:30.379"/>
        <m id="r17159361" t="d" c="31" ts="2505030151" ts-tts="25-05-03 01:51:30.379"/>
        <m id="r17159859" t="d" c="31" ts="2505030152" ts-tts="25-05-03 01:52:47.256"/>
    </dp>
</s>


<s id="2399764757688153611-2505040718-6" eva="8010101">
    <ar ct="2505040936"/>
    <dp ct="2505040940"/>
</s>


<s id="8766278971814682092-2505040938-1" eva="8010101">
    <dp ct="2505040938" l="46"/>
</s>


<s id="-3795595662574953740-2505040938-1" eva="8010101">
    <m id="r2337721" t="h" from="2412190621" to="2512131842" cat="Information" ts="2412191444" ts-tts="25-05-03 23:16:03.425" pr="2"/>
    <dp ct="2505040938" l="23"/>
</s>


<s id="-1099283276908084775-2505040935-1" eva="8010101">
    <dp cp="3" ct="2505040937" l="7"/>
</s>


<s id="7941523805643222403-2505040931-1" eva="8010101">
    <dp ct="2505040932" l="16"/>
</s>


<s id="-2221597426497896240-2505040726-5" eva="8010101">
    <ar ct="2505040927"/>
    <dp ct="2505040930"/>
</s>


<s id="-1474942826302176746-2505041325-15" eva="8010101">
    <ar ct="2505041443" l="21"/>
</s>


<s id="-5894767788106580379-2505040657-5" eva="8010101">
    <m id="r2413050" t="h" from="2505011915" to="2505052359" cat="Information" ts="2505011920" ts-tts="25-05-03 23:16:03.739" pr="2"/>
    <ar ct="2505040925">
        <m id="r17198545" t="f" c="0" ts="2505040225" ts-tts="25-05-04 02:25:25.277"/>
        <m id="r17199635" t="f" c="0" ts="2505040615" ts-tts="25-05-04 06:15:50.270"/>
        <m id="r17200022" t="f" c="0" ts="2505040644" ts-tts="25-05-04 06:44:13.611"/>
    </ar>
    <dp ct="2505040928">
        <m id="r17198545" t="f" c="0" ts="2505040225" ts-tts="25-05-04 02:25:25.277"/>
        <m id="r17199635" t="f" c="0" ts="2505040615" ts-tts="25-05-04 06:15:50.270"/>
        <m id="r17200022" t="f" c="0" ts="2505040644" ts-tts="25-05-04 06:44:13.611"/>
    </dp>
</s>


<s id="1530853161902385697-2505040734-5" eva="8010101">
    <ar ct="2505040924"/>
    <dp ct="2505040932"/>
</s>


<s id="-573116277745015774-2505040807-7" eva="8010101">
    <ar ct="2505040924" l="2"/>
</s>


<s id="5058253586448700376-2505040909-2" eva="8010101">
    <ar ct="2505040923" l="16"/>
</s>


<s id="-3801477481652564034-2505040726-4" eva="8010101">
    <ar ct="2505040917" l="10">
        <m id="r17190535" t="f" c="0" ts="2505032045" ts-tts="25-05-03 20:45:10.148"/>
        <m id="r17190536" t="f" c="1000" ts="2505032045" ts-tts="25-05-03 20:45:10.148"/>
    </ar>
    <dp ct="2505040920" l="10">
        <m id="r17190535" t="f" c="0" ts="2505032045" ts-tts="25-05-03 20:45:10.148"/>
        <m id="r17190536" t="f" c="1000" ts="2505032045" ts-tts="25-05-03 20:45:10.148"/>
    </dp>
</s>


<s id="3377561656505950600-2505040917-1" eva="8010101">
    <dp ct="2505040918" l="21"/>
</s>


<s id="2954372019686329535-2505040812-14" eva="8010101">
    <ar ct="2505040917" l="23"/>
</s>


<s id="-8949197230012960422-2505040818-14" eva="8010101">
    <ar ct="2505040916" l="46"/>
</s>


<s id="-8388579241827872740-2505040910-1" eva="8010101">
    <dp ct="2505040910" l="RE10"/>
</s>


<s id="2699537064247668917-2505040907-1" eva="8010101">
    <dp ct="2505040907" l="52"/>
</s>


<s id="1867717216919689780-2505040723-13" eva="8010101">
    <ar ct="2505040909" l="3"/>
</s>


<s id="-5096032800673842604-2505040637-3" eva="8010101">
    <ar ct="2505040908"/>
    <dp ct="2505040919"/>
</s>


<s id="309626869300548726-2505040709-23" eva="8010101">
    <ar ct="2505040855" l="20"/>
    <dp ct="2505040906" l="20"/>
</s>


<s id="-8442782341039798488-2505040806-12" eva="8010101">
    <ar ct="2505040853" l="20"/>
    <dp ct="2505040904" l="20"/>
</s>


<s id="-8441899500115711274-2505040902-1" eva="8010101">
    <dp ct="2505040902" l="56">
        <m id="r17198863" t="q" c="93" ts="2505040339" ts-tts="25-05-04 03:39:17.171"/>
    </dp>
</s>


<s id="-5173066403845695853-2505040729-16" eva="8010101">
    <ar ct="2505040856" l="56">
        <m id="r17198859" t="q" c="93" ts="2505040338" ts-tts="25-05-04 03:38:46.638"/>
    </ar>
</s>


<s id="-1124516396674037904-2505040704-4" eva="8010101">
    <ar ct="2505040848"/>
    <dp ct="2505040851"/>
</s>


<s id="5707962235511492352-2505040850-1" eva="8010101">
    <dp ct="2505040850" l="3"/>
</s>


<s id="6099491004874507241-2505040607-23" eva="8010101">
    <ar ct="2505040850" l="RE10"/>
</s>


<s id="7372708349454996763-2505040700-4" eva="8010101">
    <ar ct="2505040844"/>
    <dp ct="2505040847"/>
</s>


<s id="4400437315858566174-2505040742-13" eva="8010101">
    <ar ct="2505040846" l="52"/>
</s>


<s id="8960259525697557429-2505040725-15" eva="8010101">
    <ar ct="2505040843" l="21"/>
</s>


<s id="4183471202219985889-2505040838-1" eva="8010101">
    <dp ct="2505040838" l="23"/>
</s>


<s id="-451710820493260852-2505040838-1" eva="8010101">
    <dp ct="2505040838" l="46"/>
</s>


<s id="-396435805725507224-2505040835-1" eva="8010101">
    <dp ct="2505040835" l="16"/>
</s>


<s id="2784826577821015395-2505040833-1" eva="8010101">
    <dp ct="2505040834" l="2">
        <m id="r17190799" t="f" c="0" ts="2505032050" ts-tts="25-05-03 20:50:36.571"/>
    </dp>
</s>


<s id="8049328993498305601-2505040619-6" eva="8010101">
    <ar ct="2505040826"/>
    <dp ct="2505040831"/>
</s>


<s id="8485386043406147476-2505040802-3" eva="8010101">
    <ar ct="2505040826" l="16"/>
</s>


<s id="-6417234063813327523-2505040614-4" eva="8010101">
    <m id="r2297717" t="h" from="2412150000" to="2512132359" cat="Information" ts="2504111425" ts-tts="25-05-03 23:16:03.417" pr="2"/>
    <ar ct="2505040825"/>
    <dp ct="2505040828"/>
</s>


<s id="-7036720270093720785-2505040706-3" eva="8010101">
    <ar cpth="Nürnberg Hbf|Bamberg" ct="2505040823">
        <m id="r17126142" t="f" c="0" ts="2505021217" ts-tts="25-05-02 12:17:59.209"/>
        <m id="r17159401" t="f" c="0" ts="2505030151" ts-tts="25-05-03 01:51:30.380"/>
    </ar>
    <dp cpth="Halle(Saale)Hbf|Bitterfeld|Berlin Südkreuz|Berlin Hbf|Berlin-Spandau|Hamburg Hbf|Hamburg-Altona|Neumünster|Kiel Hbf" ct="2505040832">
        <m id="r17126142" t="f" c="0" ts="2505021217" ts-tts="25-05-02 12:17:59.209"/>
        <m id="r17159401" t="f" c="0" ts="2505030151" ts-tts="25-05-03 01:51:30.380"/>
    </dp>
</s>


<s id="3928346214463472628-2505040710-8" eva="8010101">
    <ar ct="2505040820" l="50"/>
</s>


<s id="-3876736263946883288-2505040610-5" eva="8010101">
    <ar ct="2505040815"/>
    <dp ct="2505040818"/>
</s>


<s id="5644747043881777126-2505040712-13" eva="8010101">
    <ar ct="2505040816" l="23"/>
</s>


<s id="3481697560743015092-2505040718-14" eva="8010101">
    <ar ct="2505040816" l="46"/>
</s>


<s id="-5904039450601184262-2505040553-3" eva="8010101">
    <ar cp="2" ct="2505040809"/>
    <dp cp="2" ct="2505040811"/>
</s>


<s id="-5338668929314039088-2505040809-1" eva="8010101">
    <dp ct="2505040809" l="59"/>
</s>


<s id="-3564897595617096816-2505040631-11" eva="8010101">
    <ar ct="2505040807" l="1">
        <m id="r17190779" t="f" c="0" ts="2505032049" ts-tts="25-05-03 20:50:05.467"/>
    </ar>
    <dp ct="2505040809" l="1">
        <m id="r17190779" t="f" c="0" ts="2505032049" ts-tts="25-05-03 20:50:05.467"/>
    </dp>
</s>


<s id="-3553517250721014154-2505040805-1" eva="8010101">
    <dp ct="2505040805" l="44"/>
</s>


<s id="-1396555714718086421-2505040610-9" eva="8010101">
    <ar ct="2505040805" l="29"/>
</s>


<s id="-8111475277875488150-2505040713-12" eva="8010101">
    <ar ct="2505040800" l="20"/>
    <dp ct="2505040803" l="20"/>
</s>


<s id="7861937690956949154-2505040802-1" eva="8010101">
    <dp ct="2505040802" l="55"/>
</s>


<s id="8975994796110168766-2505040609-23" eva="8010101">
    <ar ct="2505040756" l="20">
        <m id="r17199939" t="d" c="48" ts="2505040636" ts-tts="25-05-04 06:36:32.955"/>
    </ar>
    <dp ct="2505040801" l="20">
        <m id="r17199939" t="d" c="48" ts="2505040636" ts-tts="25-05-04 06:36:32.955"/>
    </dp>
</s>


<s id="947756859687964101-2505040604-9" eva="8010101">
    <ar ct="2505040745" l="1"/>
    <dp ct="2505040755" l="1"/>
</s>


<s id="-5025266593958377510-2505040752-1" eva="8010101">
    <dp ct="2505040752" l="29"/>
</s>


<s id="-7202919247926513511-2505040550-5" eva="8010101">
    <ar ct="2505040741">
        <m id="r17198846" t="f" c="0" ts="2505040333" ts-tts="25-05-04 03:33:56.261"/>
        <m id="r17199042" t="f" c="0" ts="2505040429" ts-tts="25-05-04 04:29:58.074"/>
    </ar>
    <dp ct="2505040745">
        <m id="r17198846" t="f" c="0" ts="2505040333" ts-tts="25-05-04 03:33:56.261"/>
        <m id="r17199042" t="f" c="0" ts="2505040429" ts-tts="25-05-04 04:29:58.074"/>
    </dp>
</s>


<s id="6820654971797047860-2505040738-1" eva="8010101">
    <dp ct="2505040738" l="46"/>
</s>


<s id="-7330556889082777480-2505040738-1" eva="8010101">
    <m id="r2337721" t="h" from="2412190621" to="2512131842" cat="Information" ts="2412191444" ts-tts="25-05-03 23:16:03.425" pr="2"/>
    <dp ct="2505040738" l="23"/>
</s>


<s id="-2255659203663183912-2505040735-1" eva="8010101">
    <dp ct="2505040738" l="7"/>
</s>


<s id="6141729013029977485-2505040731-1" eva="8010101">
    <dp cp="3" ct="2505040735" l="16"/>
</s>


<s id="-8657109725447363025-2505040526-5" eva="8010101">
    <ar ct="2505040733"/>
    <dp ct="2505040734"/>
</s>


<s id="8627919913190420403-2505041913-14" eva="8010101">
    <ar cp="10"/>
    <dp cp="10"/>
</s>


<s id="-5727379377570714940-2505040651-3" eva="8010101">
    <m id="r2414252" t="h" from="2505040801" to="2505040909" cat="Information" ts="2505040723" ts-tts="25-05-04 07:23:09.281" pr="2"/>
    <ar cpth="" cs="c" clt="2505040551">
        <m id="r17199487" t="d" c="36" ts="2505040551" ts-tts="25-05-04 05:51:49.027"/>
        <m id="r17199578" t="f" c="0" ts="2505040605" ts-tts="25-05-04 06:06:07.397"/>
    </ar>
    <dp cpth="" cs="c" clt="2505040551">
        <m id="r17199487" t="d" c="36" ts="2505040551" ts-tts="25-05-04 05:51:49.027"/>
        <m id="r17199578" t="f" c="0" ts="2505040605" ts-tts="25-05-04 06:06:07.397"/>
    </dp>
</s>


<s id="7944705903164501739-2505040617-7" eva="8010101">
    <ar ct="2505040720" l="3"/>
</s>


<s id="-5707788182230160293-2505042309-1" eva="8010101">
    <dp cp="8" l="20"/>
</s>


<s id="319551306123457234-2505041252-5" eva="8010101">
    <ar cpth="" cs="c" clt="2505040710">
        <m id="r17200362" t="d" c="36" ts="2505040710" ts-tts="25-05-04 07:11:06.675"/>
        <m id="r17200365" t="d" c="36" ts="2505040710" ts-tts="25-05-04 07:11:06.675"/>
    </ar>
    <dp cpth="" cs="c" clt="2505040710">
        <m id="r17200362" t="d" c="36" ts="2505040710" ts-tts="25-05-04 07:11:06.675"/>
        <m id="r17200365" t="d" c="36" ts="2505040710" ts-tts="25-05-04 07:11:06.675"/>
    </dp>
</s>


<s id="-8952284213536438559-2505040710-1" eva="8010101">
    <dp ct="2505040710" l="21"/>
</s>


<s id="4816173034586331021-2505040707-1" eva="8010101">
    <dp ct="2505040708" l="52">
        <m id="r17198894" t="q" c="93" ts="2505040342" ts-tts="25-05-04 03:42:05.382"/>
    </dp>
</s>


<s id="-3259046009005812934-2505040704-1" eva="8010101">
    <dp ct="2505040706" l="RE10"/>
</s>


<s id="-7801928170350628986-2505040604-12" eva="8010101">
    <ar ct="2505040650" l="20"/>
    <dp ct="2505040705" l="20"/>
</s>


<s id="-7051220880446097039-2505040700-1" eva="8010101">
    <dp ct="2505040700" l="56"/>
</s>


<s id="4670335008462538360-2505040653-1" eva="8010101">
    <dp ct="2505040654" l="3"/>
</s>


<s id="-1432794060798776773-2505040139-14" eva="8010101">
    <ar ppth="Cottbus Hbf|Lübben(Spreewald)|Königs Wusterhausen|Berlin-Lichtenberg|Berlin Gesundbrunnen|Berlin Hbf|Berlin Südkreuz|Lutherstadt Wittenberg Hbf|Bitterfeld|Halle(Saale)Hbf|Merseburg Hbf|Naumburg(Saale)Hbf|Weimar" pp="10" ct="2505040639" pt="2505040641">
        <m id="r17018407" t="f" c="0" ts="2504300939" ts-tts="25-04-30 09:40:09.077"/>
        <m id="r17018464" t="f" c="0" ts="2504300940" ts-tts="25-04-30 09:40:55.815"/>
        <m id="r17018465" t="f" c="1000" ts="2504300940" ts-tts="25-04-30 09:40:55.815"/>
        <m id="r17064553" t="f" c="0" ts="2505010147" ts-tts="25-05-01 01:47:52.992"/>
        <m id="r17064555" t="f" c="0" ts="2505010147" ts-tts="25-05-01 01:47:52.992"/>
        <m id="r17064556" t="f" c="1000" ts="2505010147" ts-tts="25-05-01 01:47:52.992"/>
        <m id="r17107105" t="f" c="0" ts="2505020146" ts-tts="25-05-02 01:46:57.601"/>
        <m id="r17107107" t="f" c="0" ts="2505020146" ts-tts="25-05-02 01:46:57.601"/>
        <m id="r17107108" t="f" c="1000" ts="2505020146" ts-tts="25-05-02 01:46:57.601"/>
        <m id="r17157899" t="f" c="0" ts="2505030148" ts-tts="25-05-03 01:48:25.914"/>
        <m id="r17157901" t="f" c="0" ts="2505030148" ts-tts="25-05-03 01:48:25.914"/>
        <m id="r17157902" t="f" c="1000" ts="2505030148" ts-tts="25-05-03 01:48:25.914"/>
    </ar>
    <dp ppth="Gotha|Eisenach Hbf|Fulda|Hanau Hbf|Frankfurt(Main)Süd|Mannheim Hbf|Karlsruhe Hbf|Freiburg(Breisgau) Hbf|Domodossola" pp="10" ct="2505040644" pt="2505040644">
        <m id="r17018407" t="f" c="0" ts="2504300939" ts-tts="25-04-30 09:40:09.077"/>
        <m id="r17018464" t="f" c="0" ts="2504300940" ts-tts="25-04-30 09:40:55.815"/>
        <m id="r17018465" t="f" c="1000" ts="2504300940" ts-tts="25-04-30 09:40:55.815"/>
        <m id="r17064553" t="f" c="0" ts="2505010147" ts-tts="25-05-01 01:47:52.992"/>
        <m id="r17064555" t="f" c="0" ts="2505010147" ts-tts="25-05-01 01:47:52.992"/>
        <m id="r17064556" t="f" c="1000" ts="2505010147" ts-tts="25-05-01 01:47:52.992"/>
        <m id="r17107105" t="f" c="0" ts="2505020146" ts-tts="25-05-02 01:46:57.601"/>
        <m id="r17107107" t="f" c="0" ts="2505020146" ts-tts="25-05-02 01:46:57.601"/>
        <m id="r17107108" t="f" c="1000" ts="2505020146" ts-tts="25-05-02 01:46:57.601"/>
        <m id="r17157899" t="f" c="0" ts="2505030148" ts-tts="25-05-03 01:48:25.914"/>
        <m id="r17157901" t="f" c="0" ts="2505030148" ts-tts="25-05-03 01:48:25.914"/>
        <m id="r17157902" t="f" c="1000" ts="2505030148" ts-tts="25-05-03 01:48:25.914"/>
    </dp>
    <tl t="s" o="RISSDZ" c="DZ" n="13403"/>
</s>


<s id="943205379359887506-2505040622-1" eva="8010101">
    <dp ct="2505040622" l="2"/>
</s>


<s id="8523006378069772349-2505032342-4" eva="8010101">
    <ar cpth="Mannheim Hbf|Frankfurt(Main)Süd|Fulda" ppth="Mannheim Hbf|Frankfurt(Main)Süd|Fulda" pp="10" ct="2505040430" pt="2505040244">
        <m id="r17198741" t="f" c="0" ts="2505040315" ts-tts="25-05-04 03:15:20.802"/>
        <m id="r17199044" t="f" c="0" ts="2505040430" ts-tts="25-05-04 04:30:43.987"/>
    </ar>
    <dp cpth="Leipzig Hbf|Bitterfeld|Lutherstadt Wittenberg Hbf|Berlin Südkreuz|Berlin Hbf" ppth="Leipzig Hbf|Halle(Saale)Hbf|Bitterfeld|Lutherstadt Wittenberg Hbf|Berlin Südkreuz|Berlin Hbf" pp="10" ct="2505040456" pt="2505040246">
        <m id="r17198741" t="f" c="0" ts="2505040315" ts-tts="25-05-04 03:15:20.802"/>
        <m id="r17199044" t="f" c="0" ts="2505040430" ts-tts="25-05-04 04:30:43.987"/>
    </dp>
    <tl f="F" t="p" o="NZ" c="IC" n="60409"/>
</s>


<s id="1811207988841492172-2505032342-4" eva="8010101">
    <ar cpth="Mannheim Hbf|Frankfurt(Main)Süd|Fulda" ppth="Mannheim Hbf|Frankfurt(Main)Süd|Fulda" pp="10" ct="2505040430" pt="2505040244" hi="1" wings="8523006378069772349-2505032342">
        <m id="r17198733" t="f" c="0" ts="2505040314" ts-tts="25-05-04 03:14:50.266"/>
        <m id="r17198740" t="f" c="0" ts="2505040315" ts-tts="25-05-04 03:15:20.802"/>
        <m id="r17199045" t="f" c="0" ts="2505040430" ts-tts="25-05-04 04:30:43.987"/>
    </ar>
    <dp cpth="Leipzig Hbf|Bitterfeld|Lutherstadt Wittenberg Hbf|Berlin Südkreuz|Berlin Hbf" ppth="Leipzig Hbf|Halle(Saale)Hbf|Bitterfeld|Lutherstadt Wittenberg Hbf|Berlin Südkreuz|Berlin Hbf" pp="10" ct="2505040456" pt="2505040246" hi="1" wings="8523006378069772349-2505032342">
        <m id="r17198733" t="f" c="0" ts="2505040314" ts-tts="25-05-04 03:14:50.266"/>
        <m id="r17198740" t="f" c="0" ts="2505040315" ts-tts="25-05-04 03:15:20.802"/>
        <m id="r17199045" t="f" c="0" ts="2505040430" ts-tts="25-05-04 04:30:43.987"/>
    </dp>
    <tl t="p" o="81" c="NJ" n="409"/>
</s>


<s id="5290241977442748888-2505042127-13" eva="8010101">
    <ar l="52">
        <m id="r17198912" t="q" c="93" ts="2505040343" ts-tts="25-05-04 03:44:07.660"/>
    </ar>
</s>


<s id="5331894847185138451-2505042103-6" eva="8010101">
    <m id="r2412229" t="h" from="2504300845" to="2505142359" cat="Information" ts="2504300848" ts-tts="25-05-03 23:16:03.733" pr="1"/>
</s>


<s id="-1197270886930040789-2505042103-6" eva="8010101">
    <m id="r2412229" t="h" from="2504300845" to="2505142359" cat="Information" ts="2504300848" ts-tts="25-05-03 23:16:03.733" pr="1"/>
</s>


<s id="-6153695725590346347-2505042113-12" eva="8010101">
    <ar cp="8a" l="20"/>
    <dp cp="8a" l="20"/>
</s>


<s id="5763527940252399800-2505032342-4" eva="8010101">
    <ar ppth="Mannheim Hbf|Frankfurt(Main)Süd|Fulda" pp="10" ct="2505040455" pt="2505040244" hi="1">
        <m id="r17193547" t="d" c="24" ts="2505032231" ts-tts="25-05-03 22:31:29.494"/>
        <m id="r17195539" t="f" c="0" ts="2505040018" ts-tts="25-05-04 00:18:12.187"/>
        <m id="r17196163" t="f" c="0" ts="2505040055" ts-tts="25-05-04 00:55:31.785"/>
        <m id="r17198381" t="f" c="0" ts="2505040156" ts-tts="25-05-04 01:56:06.674"/>
        <m id="r17198742" t="f" c="0" ts="2505040315" ts-tts="25-05-04 03:15:20.802"/>
        <m id="r17199046" t="f" c="0" ts="2505040430" ts-tts="25-05-04 04:30:43.987"/>
    </ar>
    <dp ppth="Leipzig Hbf|Riesa|Dresden-Neustadt|Dresden Hbf|Bad Schandau|Decin hl.n.|Usti nad Labem hl.n.|Praha-Holesovice|Praha hl.n." pp="10" ct="2505040456" pt="2505040246" hi="1">
        <m id="r17193547" t="d" c="24" ts="2505032231" ts-tts="25-05-03 22:31:29.494"/>
        <m id="r17195539" t="f" c="0" ts="2505040018" ts-tts="25-05-04 00:18:12.187"/>
        <m id="r17196163" t="f" c="0" ts="2505040055" ts-tts="25-05-04 00:55:31.785"/>
        <m id="r17198381" t="f" c="0" ts="2505040156" ts-tts="25-05-04 01:56:06.674"/>
        <m id="r17198742" t="f" c="0" ts="2505040315" ts-tts="25-05-04 03:15:20.802"/>
        <m id="r17199046" t="f" c="0" ts="2505040430" ts-tts="25-05-04 04:30:43.987"/>
    </dp>
    <tl f="F" t="p" o="81" c="EN" n="40459"/>
</s>


<s id="2484959947726432198-2505032342-4" eva="8010101">
    <ar ppth="Mannheim Hbf|Frankfurt(Main)Süd|Fulda" pp="10" ct="2505040455" pt="2505040244" hi="1" wings="5763527940252399800-2505032342">
        <m id="r17193545" t="d" c="24" ts="2505032231" ts-tts="25-05-03 22:31:29.494"/>
        <m id="r17195538" t="f" c="0" ts="2505040018" ts-tts="25-05-04 00:18:12.187"/>
        <m id="r17196164" t="f" c="0" ts="2505040055" ts-tts="25-05-04 00:55:31.784"/>
        <m id="r17198380" t="f" c="0" ts="2505040156" ts-tts="25-05-04 01:56:06.674"/>
        <m id="r17198734" t="f" c="0" ts="2505040314" ts-tts="25-05-04 03:14:50.266"/>
        <m id="r17199043" t="f" c="0" ts="2505040430" ts-tts="25-05-04 04:30:43.987"/>
    </ar>
    <dp ppth="Leipzig Hbf|Riesa|Dresden-Neustadt|Dresden Hbf|Bad Schandau|Decin hl.n.|Usti nad Labem hl.n.|Praha-Holesovice|Praha hl.n." pp="10" ct="2505040456" pt="2505040246" wings="5763527940252399800-2505032342">
        <m id="r17193545" t="d" c="24" ts="2505032231" ts-tts="25-05-03 22:31:29.494"/>
        <m id="r17195538" t="f" c="0" ts="2505040018" ts-tts="25-05-04 00:18:12.187"/>
        <m id="r17196164" t="f" c="0" ts="2505040055" ts-tts="25-05-04 00:55:31.784"/>
        <m id="r17198380" t="f" c="0" ts="2505040156" ts-tts="25-05-04 01:56:06.674"/>
        <m id="r17198734" t="f" c="0" ts="2505040314" ts-tts="25-05-04 03:14:50.266"/>
        <m id="r17199043" t="f" c="0" ts="2505040430" ts-tts="25-05-04 04:30:43.987"/>
    </dp>
    <tl f="F" t="p" o="80" c="EC" n="459"/>
</s>


<s id="8290912034684684315-2505041720-10" eva="8010101">
    <m id="r2413050" t="h" from="2505011915" to="2505052359" cat="Information" ts="2505011920" ts-tts="25-05-03 23:16:03.739" pr="2"/>
    <ar>
        <m id="r17199055" t="f" c="0" ts="2505040432" ts-tts="25-05-04 04:32:46.312"/>
    </ar>
    <dp>
        <m id="r17199055" t="f" c="0" ts="2505040432" ts-tts="25-05-04 04:32:46.312"/>
    </dp>
</s>


<s id="7108274583246193747-2505042037-10" eva="8010101">
    <m id="r2297719" t="h" from="2412150000" to="2512132359" cat="Information" ts="2504111426" ts-tts="25-05-03 23:16:03.417" pr="2"/>
    <m id="r2297722" t="h" from="2412150000" to="2512132359" cat="Information" ts="2504111427" ts-tts="25-05-03 23:16:03.417" pr="2"/>
</s>


<s id="6565901499507191012-2505042021-11" eva="8010101">
    <m id="r2359856" t="h" from="2505042021" to="2505051047" cat="Bauarbeiten" ts="2505032301" ts-tts="25-05-03 23:01:36.622" pr="1"/>
</s>


<s id="-2298891260855945727-2505041907-1" eva="8010101">
    <dp l="52">
        <m id="r17198910" t="q" c="93" ts="2505040343" ts-tts="25-05-04 03:43:52.402"/>
    </dp>
</s>


<s id="-2956592835039729223-2505041719-18" eva="8010101">
    <ar l="52">
        <m id="r17198908" t="q" c="93" ts="2505040343" ts-tts="25-05-04 03:43:21.827"/>
    </ar>
</s>


<s id="-5384842193953524382-2505041507-1" eva="8010101">
    <dp l="52">
        <m id="r17198906" t="q" c="93" ts="2505040343" ts-tts="25-05-04 03:43:21.827"/>
    </dp>
</s>


<s id="1935238254658358055-2505041929-16" eva="8010101">
    <ar l="56">
        <m id="r17198890" t="q" c="93" ts="2505040341" ts-tts="25-05-04 03:41:34.863"/>
    </ar>
</s>


<s id="-6587643016596241645-2505041802-1" eva="8010101">
    <dp l="55">
        <m id="r17198888" t="q" c="93" ts="2505040341" ts-tts="25-05-04 03:41:19.578"/>
    </dp>
</s>


<s id="-9096144324441803386-2505041634-11" eva="8010101">
    <ar l="55">
        <m id="r17198884" t="q" c="93" ts="2505040340" ts-tts="25-05-04 03:41:04.238"/>
    </ar>
</s>


<s id="4929703457209167523-2505041951-5" eva="8010101">
    <m id="r2414086" t="h" from="2505041451" to="2505050001" cat="Information" ts="2505040015" ts-tts="25-05-04 00:15:24.133" pr="2"/>
</s>


<s id="-7138074359361066746-2505041919-10" eva="8010101">
    <m id="r2413050" t="h" from="2505011915" to="2505052359" cat="Information" ts="2505011920" ts-tts="25-05-03 23:16:03.740" pr="2"/>
</s>


<s id="-7724390263517347378-2505041709-8" eva="8010101">
    <ar>
        <m id="r17198544" t="f" c="0" ts="2505040224" ts-tts="25-05-04 02:25:10.001"/>
    </ar>
    <dp>
        <m id="r17198544" t="f" c="0" ts="2505040224" ts-tts="25-05-04 02:25:10.001"/>
    </dp>
</s>


<s id="-4256402265114507618-2505032228-7" eva="8010101">
    <ar ppth="Berlin Hbf|Berlin Südkreuz|Lutherstadt Wittenberg Hbf|Bitterfeld|Leipzig Hbf|Halle(Saale)Hbf" cp="2" pp="1" ct="2505040219" pt="2505040143">
        <m id="r17196708" t="d" c="31" ts="2505040147" ts-tts="25-05-04 01:47:33.784"/>
    </ar>
    <dp ppth="Würzburg Hbf|München Ost|Salzburg Hbf|Wels Hbf|Linz Hbf|St.Pölten Hbf|Wien Meidling|Wien Hbf" cp="2" pp="1" ct="2505040220" pt="2505040145">
        <m id="r17196708" t="d" c="31" ts="2505040147" ts-tts="25-05-04 01:47:33.784"/>
    </dp>
    <tl f="F" t="p" o="80" c="IC" n="495"/>
</s>


<s id="-3331034907260447336-2505050919-13" eva="8010101">
    <ar ppth="Köln Hbf|Düsseldorf Hbf|Düsseldorf Flughafen|Duisburg Hbf|Essen Hbf|Bochum Hbf|Dortmund Hbf|Hamm(Westf)Hbf|Hannover Hbf|Göttingen|Eisenach Hbf|Gotha" pt="2505051509">
        <m id="r17188576" t="d" c="31" ts="2505031952" ts-tts="25-05-03 19:52:42.159"/>
        <m id="r17188620" t="d" c="31" ts="2505031953" ts-tts="25-05-03 19:53:13.177"/>
        <m id="r17196153" t="d" c="31" ts="2505040054" ts-tts="25-05-04 00:54:45.810"/>
        <m id="r17198178" t="d" c="31" ts="2505040151" ts-tts="25-05-04 01:51:28.652"/>
        <m id="r17198183" t="d" c="31" ts="2505040151" ts-tts="25-05-04 01:51:28.652"/>
        <m id="r17198229" t="d" c="31" ts="2505040151" ts-tts="25-05-04 01:51:44.045"/>
    </ar>
    <dp ppth="Weimar|Jena West|Jena-Göschwitz|Stadtroda|Hermsdorf-Klosterlausnitz|Gera Hbf" pt="2505051511">
        <m id="r17188576" t="d" c="31" ts="2505031952" ts-tts="25-05-03 19:52:42.159"/>
        <m id="r17188620" t="d" c="31" ts="2505031953" ts-tts="25-05-03 19:53:13.177"/>
        <m id="r17196153" t="d" c="31" ts="2505040054" ts-tts="25-05-04 00:54:45.810"/>
        <m id="r17198178" t="d" c="31" ts="2505040151" ts-tts="25-05-04 01:51:28.652"/>
        <m id="r17198183" t="d" c="31" ts="2505040151" ts-tts="25-05-04 01:51:28.652"/>
        <m id="r17198229" t="d" c="31" ts="2505040151" ts-tts="25-05-04 01:51:44.045"/>
    </dp>
    <tl f="F" t="e" o="80" c="IC" n="2575"/>
</s>


<s id="5950655788274726626-2505041818-9" eva="8010101">
    <m id="r2413050" t="h" from="2505011915" to="2505052359" cat="Information" ts="2505011920" ts-tts="25-05-03 23:16:03.739" pr="2"/>
</s>


<s id="-8716776747589038458-2505041828-10" eva="8010101">
    <m id="r2412229" t="h" from="2504300845" to="2505142359" cat="Information" ts="2504300848" ts-tts="25-05-03 23:16:03.733" pr="1"/>
</s>


<s id="-8572647521164952896-2505041828-10" eva="8010101">
    <m id="r2412229" t="h" from="2504300845" to="2505142359" cat="Information" ts="2504300848" ts-tts="25-05-03 23:16:03.732" pr="1"/>
    <m id="r2394714" t="h" from="2505010000" to="2506302359" cat="Information" ts="2504302303" ts-tts="25-05-03 23:16:03.454" pr="1"/>
</s>


<s id="-4811230494969329648-2505041804-7" eva="8010101">
    <m id="r2297756" t="h" from="2412150000" to="2512122359" cat="Information" ts="2412142300" ts-tts="25-05-03 23:16:03.417" pr="2"/>
</s>


<s id="-4822877454349863859-2505041810-5" eva="8010101">
    <m id="r2412575" t="h" from="2505041730" to="2505050300" cat="Störung" ts="2505032303" ts-tts="25-05-03 23:03:55.989" pr="1"/>
</s>


<s id="8724910087552404055-2505041836-12" eva="8010101">
    <ar cp="8" l="20"/>
</s>


<s id="455335486352975675-2505031959-5" eva="8010101">
    <m id="r2412229" t="h" from="2504300845" to="2505142359" cat="Information" ts="2504300848" ts-tts="25-05-02 23:16:04.235" pr="1"/>
    <ar ct="2505040120">
        <m id="r17188646" t="d" c="7" ts="2505031953" ts-tts="25-05-03 19:53:44.163"/>
        <m id="r17188683" t="d" c="7" ts="2505031954" ts-tts="25-05-03 19:54:46.276"/>
        <m id="r17188686" t="d" c="7" ts="2505031954" ts-tts="25-05-03 19:54:46.276"/>
        <m id="r17188698" t="f" c="0" ts="2505031954" ts-tts="25-05-03 19:55:01.889"/>
        <m id="r17188732" t="f" c="0" ts="2505031956" ts-tts="25-05-03 19:56:03.901"/>
        <m id="r17191472" t="d" c="36" ts="2505032116" ts-tts="25-05-03 21:16:25.614"/>
        <m id="r17191916" t="f" c="0" ts="2505032129" ts-tts="25-05-03 21:29:51.313"/>
    </ar>
    <dp ct="2505040123">
        <m id="r17188646" t="d" c="7" ts="2505031953" ts-tts="25-05-03 19:53:44.163"/>
        <m id="r17188683" t="d" c="7" ts="2505031954" ts-tts="25-05-03 19:54:46.276"/>
        <m id="r17188686" t="d" c="7" ts="2505031954" ts-tts="25-05-03 19:54:46.276"/>
        <m id="r17188698" t="f" c="0" ts="2505031954" ts-tts="25-05-03 19:55:01.889"/>
        <m id="r17188732" t="f" c="0" ts="2505031956" ts-tts="25-05-03 19:56:03.901"/>
        <m id="r17191472" t="d" c="36" ts="2505032116" ts-tts="25-05-03 21:16:25.614"/>
        <m id="r17191916" t="f" c="0" ts="2505032129" ts-tts="25-05-03 21:29:51.313"/>
    </dp>
</s>


<s id="-8716776747589038458-2505031828-10" eva="8010101">
    <m id="r2412229" t="h" from="2504300845" to="2505142359" cat="Information" ts="2504300848" ts-tts="25-05-02 23:16:04.235" pr="1"/>
    <ar ct="2505040121">
        <m id="r17186829" t="q" c="85" ts="2505031910" ts-tts="25-05-03 19:10:33.391"/>
    </ar>
    <dp ct="2505040123">
        <m id="r17186829" t="q" c="85" ts="2505031910" ts-tts="25-05-03 19:10:33.391"/>
    </dp>
</s>


<s id="-6751854233483108960-2505031959-5" eva="8010101">
    <m id="r2412229" t="h" from="2504300845" to="2505142359" cat="Information" ts="2504300848" ts-tts="25-05-02 23:16:04.235" pr="1"/>
    <ar ct="2505040120">
        <m id="r17186832" t="q" c="85" ts="2505031910" ts-tts="25-05-03 19:10:33.391"/>
        <m id="r17188644" t="d" c="7" ts="2505031953" ts-tts="25-05-03 19:53:44.164"/>
        <m id="r17188682" t="d" c="7" ts="2505031954" ts-tts="25-05-03 19:54:46.276"/>
        <m id="r17188684" t="d" c="7" ts="2505031954" ts-tts="25-05-03 19:54:46.276"/>
        <m id="r17188697" t="f" c="0" ts="2505031954" ts-tts="25-05-03 19:55:01.890"/>
        <m id="r17188731" t="f" c="0" ts="2505031956" ts-tts="25-05-03 19:56:03.901"/>
        <m id="r17191470" t="d" c="36" ts="2505032116" ts-tts="25-05-03 21:16:25.615"/>
        <m id="r17191915" t="f" c="0" ts="2505032129" ts-tts="25-05-03 21:29:51.313"/>
    </ar>
    <dp ct="2505040123">
        <m id="r17186832" t="q" c="85" ts="2505031910" ts-tts="25-05-03 19:10:33.391"/>
        <m id="r17188644" t="d" c="7" ts="2505031953" ts-tts="25-05-03 19:53:44.164"/>
        <m id="r17188682" t="d" c="7" ts="2505031954" ts-tts="25-05-03 19:54:46.276"/>
        <m id="r17188684" t="d" c="7" ts="2505031954" ts-tts="25-05-03 19:54:46.276"/>
        <m id="r17188697" t="f" c="0" ts="2505031954" ts-tts="25-05-03 19:55:01.890"/>
        <m id="r17188731" t="f" c="0" ts="2505031956" ts-tts="25-05-03 19:56:03.901"/>
        <m id="r17191470" t="d" c="36" ts="2505032116" ts-tts="25-05-03 21:16:25.615"/>
        <m id="r17191915" t="f" c="0" ts="2505032129" ts-tts="25-05-03 21:29:51.313"/>
    </dp>
</s>


<s id="-8572647521164952896-2505031828-10" eva="8010101">
    <m id="r2412229" t="h" from="2504300845" to="2505142359" cat="Information" ts="2504300848" ts-tts="25-05-02 23:16:04.235" pr="1"/>
    <m id="r2414059" t="h" from="2505031828" to="2505040904" cat="Information" ts="2505032109" ts-tts="25-05-03 21:09:11.517" pr="3"/>
    <m id="r2394714" t="h" from="2505010000" to="2506302359" cat="Information" ts="2504302303" ts-tts="25-05-02 23:16:04.090" pr="1"/>
    <ar ct="2505040119">
        <m id="r17186830" t="q" c="85" ts="2505031910" ts-tts="25-05-03 19:10:33.391"/>
    </ar>
    <dp ct="2505040123">
        <m id="r17186830" t="q" c="85" ts="2505031910" ts-tts="25-05-03 19:10:33.391"/>
    </dp>
</s>


<s id="3248174728705611231-2505041706-14" eva="8010101">
    <ar l="2">
        <m id="r17191664" t="f" c="0" ts="2505032121" ts-tts="25-05-03 21:21:20.219"/>
    </ar>
</s>


<s id="-2957667686167959496-2505041711-6" eva="8010101">
    <m id="r2297716" t="h" from="2412150000" to="2512132359" cat="Information" ts="2504111425" ts-tts="25-05-03 23:16:03.417" pr="2"/>
</s>


<s id="5149113403579357975-2505041703-3" eva="8010101">
    <ar cp="8" l="16"/>
</s>


<s id="-3622364796249255295-2505041727-1" eva="8010101">
    <dp cp="8" l="20"/>
</s>


<s id="-7639426630610522789-2505041608-8" eva="8010101">
    <ar l="1">
        <m id="r17191610" t="f" c="0" ts="2505032119" ts-tts="25-05-03 21:19:31.830"/>
    </ar>
    <dp l="1">
        <m id="r17191610" t="f" c="0" ts="2505032119" ts-tts="25-05-03 21:19:31.830"/>
    </dp>
</s>


<s id="8218544619443085427-2505041654-5" eva="8010101">
    <m id="r2413050" t="h" from="2505011915" to="2505052359" cat="Information" ts="2505011920" ts-tts="25-05-03 23:16:03.739" pr="2"/>
</s>


<s id="6823598612451527303-2505041616-9" eva="8010101">
    <m id="r2413050" t="h" from="2505011915" to="2505052359" cat="Information" ts="2505011920" ts-tts="25-05-03 23:16:03.739" pr="2"/>
</s>


<s id="9034802788621820812-2505041636-12" eva="8010101">
    <ar cp="8" l="20"/>
</s>


<s id="-7138074359361066746-2505031919-10" eva="8010101">
    <m id="r2413050" t="h" from="2505011915" to="2505052359" cat="Information" ts="2505011920" ts-tts="25-05-02 23:16:04.254" pr="2"/>
    <m id="r2414028" t="h" from="2505031830" to="2505032100" cat="Störung" ts="2505031934" ts-tts="25-05-03 19:34:35.748" pr="1"/>
    <ar cpth="Hamburg-Altona|Hamburg Dammtor|Hamburg Hbf|Berlin-Spandau|Berlin Hbf|Berlin Südkreuz|Lutherstadt Wittenberg Hbf|Bitterfeld|Leipzig Hbf" ct="2505032346">
        <m id="r17187513" t="d" c="2" ts="2505031927" ts-tts="25-05-03 19:27:37.164"/>
        <m id="r17193206" t="f" c="0" ts="2505032217" ts-tts="25-05-03 22:17:50.444"/>
        <m id="r17193259" t="f" c="0" ts="2505032220" ts-tts="25-05-03 22:20:09.538"/>
        <m id="r17194120" t="d" c="21" ts="2505032256" ts-tts="25-05-03 22:57:14.136"/>
        <m id="r17194189" t="f" c="0" ts="2505032259" ts-tts="25-05-03 23:00:03.933"/>
    </ar>
    <dp cpth="Eisenach Hbf|Fulda|Frankfurt(Main)Süd|Frankfurt(M) Flughafen Fernbf|Mannheim Hbf|Heidelberg Hbf|Stuttgart Hbf|Augsburg Hbf|München-Pasing|München Hbf" ct="2505032349">
        <m id="r17187513" t="d" c="2" ts="2505031927" ts-tts="25-05-03 19:27:37.164"/>
        <m id="r17193206" t="f" c="0" ts="2505032217" ts-tts="25-05-03 22:17:50.444"/>
        <m id="r17193259" t="f" c="0" ts="2505032220" ts-tts="25-05-03 22:20:09.538"/>
        <m id="r17194120" t="d" c="21" ts="2505032256" ts-tts="25-05-03 22:57:14.136"/>
        <m id="r17194189" t="f" c="0" ts="2505032259" ts-tts="25-05-03 23:00:03.933"/>
    </dp>
</s>


<s id="-1412524464226526551-2505041526-5" eva="8010101">
    <m id="r2297281" t="h" from="2412150000" to="2512132359" cat="Information" ts="2504111410" ts-tts="25-05-03 23:16:03.417" pr="2"/>
</s>


<s id="-7105580959164850016-2505041519-18" eva="8010101">
    <ar l="52">
        <m id="r17190829" t="f" c="0" ts="2505032051" ts-tts="25-05-03 20:51:07.534"/>
    </ar>
</s>


<s id="-7072391795018261274-2505041535-1" eva="8010101">
    <dp l="7">
        <m id="r17190398" t="f" c="0" ts="2505032041" ts-tts="25-05-03 20:41:17.517"/>
        <m id="r17190760" t="f" c="0" ts="2505032049" ts-tts="25-05-03 20:49:34.447"/>
    </dp>
</s>


<s id="-642457031392288379-2505041517-4" eva="8010101">
    <ar l="10">
        <m id="r17190615" t="f" c="0" ts="2505032046" ts-tts="25-05-03 20:46:58.860"/>
        <m id="r17190616" t="f" c="1000" ts="2505032046" ts-tts="25-05-03 20:46:58.860"/>
    </ar>
    <dp l="10">
        <m id="r17190615" t="f" c="0" ts="2505032046" ts-tts="25-05-03 20:46:58.860"/>
        <m id="r17190616" t="f" c="1000" ts="2505032046" ts-tts="25-05-03 20:46:58.860"/>
    </dp>
</s>


<s id="8116663660140632811-2505041503-3" eva="8010101">
    <ar cp="8a" l="16"/>
</s>


<s id="-5055284185859992368-2505041532-1" eva="8010101">
    <dp cp="8" l="16"/>
</s>

</timetable>