<?xml version="1.0" ?><timetable station="Berlin Potsdamer Platz" eva="8011118">

<s id="6444328829309271966-2504280724-14" eva="8011118">
    <ar ct="2504280907" l="8"/>
    <dp ct="2504280908" l="8"/>
</s>


<s id="6043986857315704928-2504280349-12" eva="8011118">
    <ar ct="2504280515" l="5"/>
    <dp ct="2504280516" l="5"/>
</s>


<s id="6699077307981861871-2504281901-21" eva="8011118">
    <m id="r2333137" t="h" from="2412150000" to="2506202358" cat="Information" ts="2412142302" ts-tts="25-04-27 23:16:04.040" pr="2"/>
</s>


<s id="-5926392827752150163-2504281936-2" eva="8011118">
    <m id="r2333137" t="h" from="2412150000" to="2506202358" cat="Information" ts="2412142302" ts-tts="25-04-27 23:16:04.040" pr="2"/>
</s>


<s id="4828162981433498373-2504281141-2" eva="8011118">
    <ar l="14">
        <m id="r16900965" t="q" c="95" ts="2504280303" ts-tts="25-04-28 03:03:14.082"/>
    </ar>
    <dp l="14">
        <m id="r16900965" t="q" c="95" ts="2504280303" ts-tts="25-04-28 03:03:14.082"/>
    </dp>
</s>


<s id="7506805165296073510-2504280842-2" eva="8011118">
    <ar l="14">
        <m id="r16900961" t="q" c="95" ts="2504280303" ts-tts="25-04-28 03:03:14.082"/>
    </ar>
    <dp l="14">
        <m id="r16900961" t="q" c="95" ts="2504280303" ts-tts="25-04-28 03:03:14.082"/>
    </dp>
</s>


<s id="-742209400199427317-2504280541-2" eva="8011118">
    <ar l="14">
        <m id="r16900959" t="q" c="95" ts="2504280303" ts-tts="25-04-28 03:03:14.082"/>
    </ar>
    <dp l="14">
        <m id="r16900959" t="q" c="95" ts="2504280303" ts-tts="25-04-28 03:03:14.082"/>
    </dp>
</s>


<s id="1770003635446785382-2504281027-10" eva="8011118">
    <ar l="14">
        <m id="r16900957" t="q" c="95" ts="2504280303" ts-tts="25-04-28 03:03:14.081"/>
    </ar>
    <dp l="14">
        <m id="r16900957" t="q" c="95" ts="2504280303" ts-tts="25-04-28 03:03:14.081"/>
    </dp>
</s>


<s id="8921008209203984976-2504280722-10" eva="8011118">
    <ar l="14">
        <m id="r16900963" t="q" c="95" ts="2504280303" ts-tts="25-04-28 03:03:14.081"/>
    </ar>
    <dp l="14">
        <m id="r16900963" t="q" c="95" ts="2504280303" ts-tts="25-04-28 03:03:14.081"/>
    </dp>
</s>


<s id="-2371969129715118406-2504280645-2" eva="8011118">
    <ar ct="2504280647" l="8"/>
    <dp ct="2504280648" l="8"/>
</s>


<s id="-5046758686245647563-2504280613-20" eva="8011118">
    <ar ct="2504280806" l="8"/>
    <dp ct="2504280807" l="8"/>
</s>


<s id="-482901495067885548-2504280542-2" eva="8011118">
    <ar ct="2504280544" l="8"/>
    <dp ct="2504280545" l="8"/>
</s>


<s id="-8962707668669101601-2504280535-14" eva="8011118">
    <ar ct="2504280707" l="8"/>
    <dp ct="2504280708" l="8"/>
</s>


<s id="5428913058894445078-2504281234-13" eva="8011118">
    <ar l="5">
        <m id="r16899730" t="f" c="0" ts="2504280132" ts-tts="25-04-28 01:32:52.924"/>
    </ar>
    <dp l="5">
        <m id="r16899730" t="f" c="0" ts="2504280132" ts-tts="25-04-28 01:32:52.924"/>
    </dp>
</s>


<s id="5833177948138978538-2504281735-2" eva="8011118">
    <m id="r2333137" t="h" from="2412150000" to="2506202358" cat="Information" ts="2412142302" ts-tts="25-04-27 23:16:04.040" pr="2"/>
    <ar l="5">
        <m id="r16899258" t="f" c="0" ts="2504280043" ts-tts="25-04-28 00:43:52.519"/>
    </ar>
    <dp l="5">
        <m id="r16899258" t="f" c="0" ts="2504280043" ts-tts="25-04-28 00:43:52.519"/>
    </dp>
</s>


<s id="-4831004071712342153-2504281701-23" eva="8011118">
    <m id="r2333137" t="h" from="2412150000" to="2506202358" cat="Information" ts="2412142302" ts-tts="25-04-27 23:16:04.040" pr="2"/>
</s>


<s id="-4398534199326013641-2504280007-11" eva="8011118">
    <ar ct="2504280107" l="8"/>
    <dp ct="2504280108" l="8"/>
</s>


<s id="7380714817348894342-2504281434-13" eva="8011118">
    <ar l="5">
        <m id="r16899541" t="f" c="0" ts="2504280105" ts-tts="25-04-28 01:05:13.637"/>
    </ar>
    <dp l="5">
        <m id="r16899541" t="f" c="0" ts="2504280105" ts-tts="25-04-28 01:05:13.637"/>
    </dp>
</s>


<s id="-42808539263809878-2504281636-2" eva="8011118">
    <ar l="5">
        <m id="r16899538" t="f" c="0" ts="2504280104" ts-tts="25-04-28 01:04:42.709"/>
    </ar>
    <dp l="5">
        <m id="r16899538" t="f" c="0" ts="2504280104" ts-tts="25-04-28 01:04:42.709"/>
    </dp>
</s>


<s id="-7597557449357820560-2504281236-2" eva="8011118">
    <ar l="5">
        <m id="r16899523" t="f" c="0" ts="2504280103" ts-tts="25-04-28 01:04:11.735"/>
    </ar>
    <dp l="5">
        <m id="r16899523" t="f" c="0" ts="2504280103" ts-tts="25-04-28 01:04:11.735"/>
    </dp>
</s>


<s id="3976725221858184001-2504281036-2" eva="8011118">
    <ar l="5">
        <m id="r16899373" t="f" c="0" ts="2504280051" ts-tts="25-04-28 00:52:04.878"/>
        <m id="r16899382" t="f" c="0" ts="2504280052" ts-tts="25-04-28 00:52:50.873"/>
    </ar>
    <dp l="5">
        <m id="r16899373" t="f" c="0" ts="2504280051" ts-tts="25-04-28 00:52:04.878"/>
        <m id="r16899382" t="f" c="0" ts="2504280052" ts-tts="25-04-28 00:52:50.873"/>
    </dp>
</s>


<s id="-5994517840461646746-2504280048-2" eva="8011118">
    <ar ct="2504280051" l="8"/>
    <dp ct="2504280052" l="8"/>
</s>


<s id="4017972157379463891-2504280042-2" eva="8011118">
    <ar ct="2504280045" l="3"/>
    <dp ct="2504280045" l="3"/>
</s>


<s id="-3021218213597977430-2504281501-23" eva="8011118">
    <m id="r2333137" t="h" from="2412150000" to="2506202358" cat="Information" ts="2412142302" ts-tts="25-04-27 23:16:04.040" pr="2"/>
    <ar l="5">
        <m id="r16899251" t="f" c="0" ts="2504280043" ts-tts="25-04-28 00:43:21.653"/>
    </ar>
    <dp l="5">
        <m id="r16899251" t="f" c="0" ts="2504280043" ts-tts="25-04-28 00:43:21.653"/>
    </dp>
</s>


<s id="-6523479487059033919-2504281301-23" eva="8011118">
    <m id="r2333137" t="h" from="2412150000" to="2506202358" cat="Information" ts="2412142302" ts-tts="25-04-27 23:16:04.040" pr="2"/>
    <ar l="5">
        <m id="r16899235" t="f" c="0" ts="2504280042" ts-tts="25-04-28 00:42:20.314"/>
    </ar>
    <dp l="5">
        <m id="r16899235" t="f" c="0" ts="2504280042" ts-tts="25-04-28 00:42:20.314"/>
    </dp>
</s>


<s id="3626444551768966269-2504281101-23" eva="8011118">
    <m id="r2333137" t="h" from="2412150000" to="2506202358" cat="Information" ts="2412142302" ts-tts="25-04-27 23:16:04.040" pr="2"/>
    <ar l="5">
        <m id="r16899228" t="f" c="0" ts="2504280041" ts-tts="25-04-28 00:41:49.584"/>
    </ar>
    <dp l="5">
        <m id="r16899228" t="f" c="0" ts="2504280041" ts-tts="25-04-28 00:41:49.584"/>
    </dp>
</s>


<s id="-1481327194743506431-2504281136-2" eva="8011118">
    <m id="r2333137" t="h" from="2412150000" to="2506202358" cat="Information" ts="2412142302" ts-tts="25-04-27 23:16:04.040" pr="2"/>
    <ar l="5">
        <m id="r16899196" t="f" c="0" ts="2504280040" ts-tts="25-04-28 00:40:17.362"/>
        <m id="r16899211" t="f" c="0" ts="2504280040" ts-tts="25-04-28 00:41:03.405"/>
    </ar>
    <dp l="5">
        <m id="r16899196" t="f" c="0" ts="2504280040" ts-tts="25-04-28 00:40:17.362"/>
        <m id="r16899211" t="f" c="0" ts="2504280040" ts-tts="25-04-28 00:41:03.405"/>
    </dp>
</s>


<s id="-8727695767215884525-2504280438-2" eva="8011118">
    <ar ct="2504280440" l="8"/>
    <dp ct="2504280441" l="8"/>
</s>


<s id="-5749564141408552110-2504280935-2" eva="8011118">
    <m id="r2333137" t="h" from="2412150000" to="2506202358" cat="Information" ts="2412142302" ts-tts="25-04-27 23:16:04.040" pr="2"/>
    <ar l="5">
        <m id="r16899042" t="f" c="0" ts="2504280037" ts-tts="25-04-28 00:37:27.481"/>
    </ar>
    <dp l="5">
        <m id="r16899042" t="f" c="0" ts="2504280037" ts-tts="25-04-28 00:37:27.481"/>
    </dp>
</s>


<s id="4750786041615116600-2504280701-23" eva="8011118">
    <m id="r2333137" t="h" from="2412150000" to="2506202358" cat="Information" ts="2412142302" ts-tts="25-04-27 23:16:04.040" pr="2"/>
    <ar l="5">
        <m id="r16899023" t="f" c="0" ts="2504280036" ts-tts="25-04-28 00:36:10.588"/>
    </ar>
    <dp l="5">
        <m id="r16899023" t="f" c="0" ts="2504280036" ts-tts="25-04-28 00:36:10.588"/>
    </dp>
</s>


<s id="6481218405205876469-2504280736-2" eva="8011118">
    <m id="r2333137" t="h" from="2412150000" to="2506202358" cat="Information" ts="2412142302" ts-tts="25-04-27 23:16:04.040" pr="2"/>
    <ar l="5">
        <m id="r16899016" t="f" c="0" ts="2504280035" ts-tts="25-04-28 00:35:24.471"/>
    </ar>
    <dp l="5">
        <m id="r16899016" t="f" c="0" ts="2504280035" ts-tts="25-04-28 00:35:24.471"/>
    </dp>
</s>


<s id="4662689697193213288-2504281033-9" eva="8011118">
    <ar l="3">
        <m id="r16899003" t="f" c="0" ts="2504280034" ts-tts="25-04-28 00:34:38.433"/>
    </ar>
    <dp l="3">
        <m id="r16899003" t="f" c="0" ts="2504280034" ts-tts="25-04-28 00:34:38.433"/>
    </dp>
</s>


<s id="-5755109118508219310-2504281503-15" eva="8011118">
    <ar l="3">
        <m id="r16898990" t="f" c="0" ts="2504280033" ts-tts="25-04-28 00:33:21.657"/>
    </ar>
    <dp l="3">
        <m id="r16898990" t="f" c="0" ts="2504280033" ts-tts="25-04-28 00:33:21.657"/>
    </dp>
</s>


<s id="7022789033164733279-2504272300-18" eva="8011118">
    <ar ct="2504280031" l="3"/>
    <dp ct="2504280032" l="3"/>
</s>


<s id="2500312828214632977-2504281202-11" eva="8011118">
    <ar l="4">
        <m id="r16898943" t="f" c="0" ts="2504280029" ts-tts="25-04-28 00:29:15.977"/>
    </ar>
    <dp l="4">
        <m id="r16898943" t="f" c="0" ts="2504280029" ts-tts="25-04-28 00:29:15.977"/>
    </dp>
</s>


<s id="-3391002097767000204-2504280914-15" eva="8011118">
    <ar l="4">
        <m id="r16898921" t="f" c="0" ts="2504280028" ts-tts="25-04-28 00:28:13.378"/>
    </ar>
    <dp l="4">
        <m id="r16898921" t="f" c="0" ts="2504280028" ts-tts="25-04-28 00:28:13.378"/>
    </dp>
</s>


<s id="-5790449521992640924-2504280413-20" eva="8011118">
    <ar ct="2504280606" l="8"/>
    <dp ct="2504280607" l="8"/>
</s>


<s id="-7440650316530548951-2504280407-11" eva="8011118">
    <ar ct="2504280507" l="8"/>
    <dp ct="2504280508" l="8"/>
</s>


<s id="1037108886086847422-2504272207-11" eva="8011118">
    <ar ct="2504272307" l="8">
        <m id="r16898188" t="d" c="43" ts="2504272355" ts-tts="25-04-27 23:56:04.840"/>
    </ar>
    <dp ct="2504272310" l="8">
        <m id="r16898188" t="d" c="43" ts="2504272355" ts-tts="25-04-27 23:56:04.840"/>
    </dp>
</s>


<s id="-5181293298076149570-2504272333-2" eva="8011118">
    <ar ct="2504272335" l="3">
        <m id="r16894885" t="f" c="0" ts="2504272105" ts-tts="25-04-27 21:06:06.545"/>
    </ar>
    <dp ct="2504272336" l="3">
        <m id="r16894885" t="f" c="0" ts="2504272105" ts-tts="25-04-27 21:06:06.545"/>
    </dp>
</s>


<s id="-1529742394438274390-2504272239-10" eva="8011118">
    <ar ct="2504272319" l="10"/>
    <dp ct="2504272320" l="10"/>
</s>


<s id="1729944272838089546-2504280700-16" eva="8011118">
    <m id="r2333213" t="h" from="2412160839" to="2505301141" cat="Information" ts="2412152302" ts-tts="25-04-27 23:16:04.041" pr="2"/>
</s>


<s id="1957499721071006901-2504280536-2" eva="8011118">
    <m id="r2333137" t="h" from="2412150000" to="2506202358" cat="Information" ts="2412142302" ts-tts="25-04-27 23:16:04.040" pr="2"/>
</s>


<s id="-8363173508708157613-2504280427-13" eva="8011118">
    <m id="r2333137" t="h" from="2412150000" to="2506202358" cat="Information" ts="2412142302" ts-tts="25-04-27 23:16:04.040" pr="2"/>
</s>


<s id="5784216260643262097-2504281536-2" eva="8011118">
    <m id="r2333137" t="h" from="2412150000" to="2506202358" cat="Information" ts="2412142302" ts-tts="25-04-27 23:16:04.040" pr="2"/>
</s>


<s id="4076161180114307688-2504281336-2" eva="8011118">
    <m id="r2333137" t="h" from="2412150000" to="2506202358" cat="Information" ts="2412142302" ts-tts="25-04-27 23:16:04.040" pr="2"/>
</s>


<s id="2832703507506315922-2504280901-23" eva="8011118">
    <m id="r2333137" t="h" from="2412150000" to="2506202358" cat="Information" ts="2412142302" ts-tts="25-04-27 23:16:04.040" pr="2"/>
</s>


<s id="1375556554873415977-2504280501-21" eva="8011118">
    <m id="r2333137" t="h" from="2412150000" to="2506202358" cat="Information" ts="2412142302" ts-tts="25-04-27 23:16:04.040" pr="2"/>
</s>


<s id="-3875282309218874989-2504272303-2" eva="8011118">
    <m id="r2410697" t="h" from="2504272139" to="2504272350" cat="Information" ts="2504270850" ts-tts="25-04-27 08:50:50.160" pr="2"/>
    <ar ct="2504272307" l="10">
        <m id="r16875250" t="q" c="95" ts="2504270950" ts-tts="25-04-27 09:50:52.270"/>
        <m id="r16896883" t="q" c="88" ts="2504272239" ts-tts="25-04-27 22:39:28.120"/>
    </ar>
    <dp ct="2504272308" l="10">
        <m id="r16875250" t="q" c="95" ts="2504270950" ts-tts="25-04-27 09:50:52.270"/>
        <m id="r16896883" t="q" c="88" ts="2504272239" ts-tts="25-04-27 22:39:28.120"/>
    </dp>
</s>


<s id="2850484104831128676-2504272203-11" eva="8011118">
    <ar ct="2504272301" l="4">
        <m id="r16896367" t="d" c="45" ts="2504272214" ts-tts="25-04-27 22:14:42.467"/>
        <m id="r16896852" t="d" c="45" ts="2504272237" ts-tts="25-04-27 22:37:24.420"/>
    </ar>
    <dp ct="2504272303" l="4">
        <m id="r16896367" t="d" c="45" ts="2504272214" ts-tts="25-04-27 22:14:42.467"/>
        <m id="r16896852" t="d" c="45" ts="2504272237" ts-tts="25-04-27 22:37:24.420"/>
    </dp>
</s>


<s id="-6488165301808617795-2504272245-2" eva="8011118">
    <ar ct="2504272247" l="8"/>
    <dp ct="2504272248" l="8"/>
</s>


<s id="8056951850572590006-2504272236-2" eva="8011118">
    <ar ct="2504272240" l="5">
        <m id="r16881425" t="q" c="74" ts="2504271406" ts-tts="25-04-27 14:07:01.222"/>
    </ar>
    <dp ct="2504272241" l="5">
        <m id="r16881425" t="q" c="74" ts="2504271406" ts-tts="25-04-27 14:07:01.222"/>
    </dp>
</s>


<s id="5912411555827437823-2504272231-2" eva="8011118">
    <ar ct="2504272236" l="3"/>
    <dp ct="2504272236" l="3"/>
</s>


<s id="6281486420573721544-2504272100-15" eva="8011118">
    <ar ct="2504272229" l="3">
        <m id="r16894877" t="f" c="0" ts="2504272105" ts-tts="25-04-27 21:05:51.113"/>
        <m id="r16896415" t="d" c="43" ts="2504272216" ts-tts="25-04-27 22:16:15.509"/>
    </ar>
    <dp ct="2504272230" l="3">
        <m id="r16894877" t="f" c="0" ts="2504272105" ts-tts="25-04-27 21:05:51.113"/>
        <m id="r16896415" t="d" c="43" ts="2504272216" ts-tts="25-04-27 22:16:15.509"/>
    </dp>
</s>


<s id="5893444450490108481-2504272139-10" eva="8011118">
    <m id="r2410697" t="h" from="2504272139" to="2504272350" cat="Information" ts="2504270850" ts-tts="25-04-27 08:50:50.160" pr="2"/>
    <ar cp="2" ct="2504272221" l="10">
        <m id="r16875247" t="q" c="95" ts="2504270950" ts-tts="25-04-27 09:50:21.541"/>
    </ar>
    <dp cp="2" ct="2504272221" l="10">
        <m id="r16875247" t="q" c="95" ts="2504270950" ts-tts="25-04-27 09:50:21.541"/>
    </dp>
</s>


<s id="6699077307981861871-2504271901-21" eva="8011118">
    <m id="r2333137" t="h" from="2412150000" to="2506202358" cat="Information" ts="2412142302" ts-tts="25-04-26 23:16:03.036" pr="2"/>
    <ar ct="2504272214" l="5">
        <m id="r16881416" t="q" c="73" ts="2504271406" ts-tts="25-04-27 14:06:30.371"/>
        <m id="r16893341" t="d" c="21" ts="2504272005" ts-tts="25-04-27 20:05:16.279"/>
    </ar>
    <dp ct="2504272215" l="5">
        <m id="r16881416" t="q" c="73" ts="2504271406" ts-tts="25-04-27 14:06:30.371"/>
        <m id="r16893341" t="d" c="21" ts="2504272005" ts-tts="25-04-27 20:05:16.279"/>
    </dp>
</s>


<s id="-5242198403931029577-2504272202-2" eva="8011118">
    <ar ct="2504272207" l="10"/>
    <dp ct="2504272208" l="10"/>
</s>


<s id="4677837088339697113-2504272108-10" eva="8011118">
    <ar ct="2504272150" l="10"/>
    <dp ct="2504272151" l="10"/>
</s>


<s id="416223917512060305-2504272103-8" eva="8011118">
    <ar ct="2504272148" l="4"/>
    <dp ct="2504272149" l="4"/>
</s>


<s id="-6065240417646439631-2504272142-2" eva="8011118">
    <ar ct="2504272145" l="8"/>
    <dp ct="2504272145" l="8"/>
</s>


<s id="-6222332847854573906-2504272135-2" eva="8011118">
    <m id="r2333137" t="h" from="2412150000" to="2506202358" cat="Information" ts="2412142302" ts-tts="25-04-26 23:16:03.036" pr="2"/>
    <ar ct="2504272142" l="5"/>
    <dp ct="2504272143" l="5"/>
</s>


<s id="6236672890872799229-2504272133-2" eva="8011118">
    <ar ct="2504272137" l="3"/>
    <dp ct="2504272137" l="3"/>
</s>


<s id="8691778266180455341-2504271834-13" eva="8011118">
    <ar ct="2504272127" l="5">
        <m id="r16891634" t="d" c="21" ts="2504271909" ts-tts="25-04-27 19:09:46.334"/>
        <m id="r16895155" t="f" c="0" ts="2504272116" ts-tts="25-04-27 21:16:09.660"/>
    </ar>
    <dp ct="2504272127" l="5">
        <m id="r16891634" t="d" c="21" ts="2504271909" ts-tts="25-04-27 19:09:46.334"/>
        <m id="r16895155" t="f" c="0" ts="2504272116" ts-tts="25-04-27 21:16:09.660"/>
    </dp>
</s>


<s id="-4591667838043678587-2504272056-7" eva="8011118">
    <ar ct="2504272124" l="3"/>
    <dp ct="2504272125" l="3"/>
</s>


<s id="6336952276054459561-2504272027-10" eva="8011118">
    <ar ct="2504272113" l="14"/>
    <dp ct="2504272114" l="14"/>
</s>


<s id="7389501989890790418-2504272002-11" eva="8011118">
    <ar ct="2504272108" l="4">
        <m id="r16894000" t="d" c="45" ts="2504272031" ts-tts="25-04-27 20:31:19.915"/>
    </ar>
    <dp ct="2504272109" l="4">
        <m id="r16894000" t="d" c="45" ts="2504272031" ts-tts="25-04-27 20:31:19.915"/>
    </dp>
</s>


<s id="2284985446713615080-2504272007-11" eva="8011118">
    <ar ct="2504272107" l="8"/>
    <dp ct="2504272108" l="8"/>
</s>


<s id="-2689124841204082392-2504272102-2" eva="8011118">
    <ar ct="2504272106" l="10"/>
    <dp ct="2504272107" l="10"/>
</s>


<s id="622999945929091283-2504272008-10" eva="8011118">
    <ar ct="2504272051" l="10"/>
    <dp ct="2504272051" l="10"/>
</s>


<s id="-2032569237475830480-2504271914-15" eva="8011118">
    <m id="r2410695" t="h" from="2504270714" to="2504272152" cat="Information" ts="2504270841" ts-tts="25-04-27 08:41:20.810" pr="2"/>
    <ar ct="2504272049" l="4">
        <m id="r16874769" t="q" c="73" ts="2504270929" ts-tts="25-04-27 09:29:19.395"/>
    </ar>
    <dp ct="2504272050" l="4">
        <m id="r16874769" t="q" c="73" ts="2504270929" ts-tts="25-04-27 09:29:19.395"/>
    </dp>
</s>


<s id="-663717987117295661-2504272045-2" eva="8011118">
    <ar ct="2504272047" l="8"/>
    <dp ct="2504272048" l="8"/>
</s>


<s id="-1001326572688500578-2504272041-2" eva="8011118">
    <m id="r2410672" t="h" from="2504270000" to="2504272359" cat="Information" ts="2504270749" ts-tts="25-04-27 07:50:03.472" pr="2"/>
    <ar ct="2504272045" l="14">
        <m id="r16875235" t="q" c="95" ts="2504270949" ts-tts="25-04-27 09:50:06.024"/>
    </ar>
    <dp ct="2504272046" l="14">
        <m id="r16875235" t="q" c="95" ts="2504270949" ts-tts="25-04-27 09:50:06.024"/>
    </dp>
</s>


<s id="-15038667024154512-2504272032-2" eva="8011118">
    <ar cp="2" ct="2504272041" l="3"/>
    <dp cp="2" ct="2504272042" l="3"/>
</s>


<s id="8930734303365215950-2504272036-2" eva="8011118">
    <ar ct="2504272040" l="5"/>
    <dp ct="2504272042" l="5"/>
</s>


<s id="-4058401902925227636-2504271905-15" eva="8011118">
    <ar ct="2504272028" l="3">
        <m id="r16891560" t="d" c="45" ts="2504271907" ts-tts="25-04-27 19:07:57.851"/>
    </ar>
    <dp ct="2504272029" l="3">
        <m id="r16891560" t="d" c="45" ts="2504271907" ts-tts="25-04-27 19:07:57.851"/>
    </dp>
</s>


<s id="-4831004071712342153-2504271701-23" eva="8011118">
    <m id="r2333137" t="h" from="2412150000" to="2506202358" cat="Information" ts="2412142302" ts-tts="25-04-26 23:16:03.036" pr="2"/>
    <ar ct="2504272021" l="5">
        <m id="r16884351" t="d" c="48" ts="2504271547" ts-tts="25-04-27 15:47:14.762"/>
        <m id="r16889954" t="d" c="21" ts="2504271829" ts-tts="25-04-27 18:29:44.665"/>
    </ar>
    <dp ct="2504272022" l="5">
        <m id="r16884351" t="d" c="48" ts="2504271547" ts-tts="25-04-27 15:47:14.762"/>
        <m id="r16889954" t="d" c="21" ts="2504271829" ts-tts="25-04-27 18:29:44.665"/>
    </dp>
</s>


<s id="-6040350043200287757-2504271922-10" eva="8011118">
    <m id="r2410672" t="h" from="2504270000" to="2504272359" cat="Information" ts="2504270749" ts-tts="25-04-27 07:50:03.472" pr="2"/>
    <ar ct="2504272012" l="14">
        <m id="r16875230" t="q" c="95" ts="2504270949" ts-tts="25-04-27 09:49:35.139"/>
        <m id="r16892433" t="d" c="43" ts="2504271934" ts-tts="25-04-27 19:34:33.897"/>
    </ar>
    <dp ct="2504272013" l="14">
        <m id="r16875230" t="q" c="95" ts="2504270949" ts-tts="25-04-27 09:49:35.139"/>
        <m id="r16892433" t="d" c="43" ts="2504271934" ts-tts="25-04-27 19:34:33.897"/>
    </dp>
</s>


<s id="2281524756355985951-2504271904-10" eva="8011118">
    <ar ct="2504272006" l="4">
        <m id="r16870343" t="f" c="0" ts="2504270206" ts-tts="25-04-27 02:06:19.508"/>
        <m id="r16891768" t="d" c="43" ts="2504271914" ts-tts="25-04-27 19:14:09.797"/>
    </ar>
    <dp ct="2504272007" l="4">
        <m id="r16870343" t="f" c="0" ts="2504270206" ts-tts="25-04-27 02:06:19.508"/>
        <m id="r16891768" t="d" c="43" ts="2504271914" ts-tts="25-04-27 19:14:09.797"/>
    </dp>
</s>


<s id="-3187017470803477618-2504272002-2" eva="8011118">
    <ar ct="2504272005" l="10"/>
    <dp ct="2504272007" l="10"/>
</s>


<s id="2346955522981538962-2504271903-8" eva="8011118">
    <ar ct="2504272000" l="4">
        <m id="r16892691" t="d" c="43" ts="2504271943" ts-tts="25-04-27 19:43:51.460"/>
    </ar>
    <dp ct="2504272002" l="4">
        <m id="r16892691" t="d" c="43" ts="2504271943" ts-tts="25-04-27 19:43:51.460"/>
    </dp>
</s>


<s id="3349865719633428304-2504271935-2" eva="8011118">
    <ar ct="2504271953" l="3">
        <m id="r16892734" t="d" c="48" ts="2504271944" ts-tts="25-04-27 19:44:37.973"/>
    </ar>
    <dp ct="2504271954" l="3">
        <m id="r16892734" t="d" c="48" ts="2504271944" ts-tts="25-04-27 19:44:37.973"/>
    </dp>
</s>


<s id="6617695006145501165-2504271941-2" eva="8011118">
    <ar ct="2504271945" l="14"/>
    <dp ct="2504271948" l="14"/>
</s>


<s id="-7147339730808320662-2504271802-11" eva="8011118">
    <ar ct="2504271912" l="4">
        <m id="r16888043" t="f" c="0" ts="2504271737" ts-tts="25-04-27 17:37:35.971"/>
    </ar>
    <dp ct="2504271913" l="4">
        <m id="r16888043" t="f" c="0" ts="2504271737" ts-tts="25-04-27 17:37:35.971"/>
    </dp>
</s>


<s id="2882319538905299608-2504271836-2" eva="8011118">
    <ar ct="2504271844" l="5"/>
    <dp ct="2504271847" l="5"/>
</s>


<s id="4022568768308180599-2504271832-2" eva="8011118">
    <ar cp="2" ct="2504271842" l="3">
        <m id="r16875080" t="f" c="0" ts="2504270943" ts-tts="25-04-27 09:43:25.970"/>
        <m id="r16888778" t="d" c="58" ts="2504271759" ts-tts="25-04-27 17:59:16.248"/>
    </ar>
    <dp cp="2" ct="2504271842" l="3">
        <m id="r16875080" t="f" c="0" ts="2504270943" ts-tts="25-04-27 09:43:25.970"/>
        <m id="r16888778" t="d" c="58" ts="2504271759" ts-tts="25-04-27 17:59:16.248"/>
    </dp>
</s>


<s id="-5926392827752150163-2504271936-2" eva="8011118">
    <m id="r2333137" t="h" from="2412150000" to="2506202358" cat="Information" ts="2412142302" ts-tts="25-04-26 23:16:03.036" pr="2"/>
    <ar cpth="" cs="c" clt="2504271827" l="5">
        <m id="r16889896" t="d" c="8" ts="2504271827" ts-tts="25-04-27 18:28:11.742"/>
    </ar>
    <dp cpth="Berlin Gesundbrunnen|Oranienburg|Löwenberg(Mark)|Gransee|Fürstenberg(Havel)|Neustrelitz Hbf|Blankensee(Meckl)|Cammin(Meckl)|Burg Stargard(Meckl)|Neubrandenburg|Gnevkow|Utzedel|Demmin|Rakow|Grimmen|Wittenhagen|Elmenhorst|Zarrendorf|Stralsund Hbf" cs="c" clt="2504271827" l="5">
        <m id="r16889896" t="d" c="8" ts="2504271827" ts-tts="25-04-27 18:28:11.742"/>
    </dp>
</s>


<s id="-7921721817666204816-2504271942-2" eva="8011118">
    <ar cpth="" ct="2504271944" cs="c" clt="2504271814" l="8"/>
    <dp cpth="Berlin Südkreuz|Berlin-Lichterfelde Ost|Blankenfelde(Teltow-Fläming)|Dahlewitz|Rangsdorf|Dabendorf|Zossen|Wünsdorf-Waldstadt|Neuhof(b Zossen)|Baruth(Mark)|Klasdorf Glashütte|Golßen(Niederlausitz)|Drahnsdorf|Luckau-Uckro|Walddrehna|Doberlug-Kirchhain|Rückersdorf|Hohenleipisch|Elsterwerda" ct="2504271945" cs="c" clt="2504271814" l="8"/>
</s>


<s id="5833177948138978538-2504271735-2" eva="8011118">
    <m id="r2333137" t="h" from="2412150000" to="2506202358" cat="Information" ts="2412142302" ts-tts="25-04-26 23:16:03.036" pr="2"/>
    <ar ct="2504271746" l="5">
        <m id="r16870465" t="f" c="0" ts="2504270224" ts-tts="25-04-27 02:24:25.304"/>
        <m id="r16886053" t="d" c="48" ts="2504271641" ts-tts="25-04-27 16:41:39.201"/>
    </ar>
    <dp ct="2504271747" l="5">
        <m id="r16870465" t="f" c="0" ts="2504270224" ts-tts="25-04-27 02:24:25.304"/>
        <m id="r16886053" t="d" c="48" ts="2504271641" ts-tts="25-04-27 16:41:39.201"/>
    </dp>
</s>

</timetable>